Workbook

Sheet Leia-me
A1: Controle de Empresas, Colaboradores, Obras e Documentação — VerticalParts
A2: v2 — inclui os vencimentos reais (GERAL (3)) e os envios por obra (6 abas) de Controle de Documentos.xlsx
A4: O QUE MUDOU NESTA VERSAO (v2)
A5: • Docs_Empresa e Docs_Colaborador agora tem os vencimentos REAIS extraidos da aba GERAL (3) de Controle de Documentos.xlsx (41 colaboradores, ate 28 documentos cada).
A6: • Envios_Obra_Documento agora tem os registros REAIS das 6 abas por obra (Metro SP, Metro BH, Hospital SC, Paraguacu, Vip Gales, Goiabeiras) — 274 eventos de documento x obra.
A7: • Obra_Empresa agora tem as alocacoes reais observadas (qual empresa esta em qual obra).
A8: • Empresas e Colaboradores ganharam registros novos que so apareciam em Controle de Documentos.xlsx e nao estavam em Planilha Organizar (1).xlsx — marcados em azul claro, com comentario explicando a origem.
A9: • Doc_Catalogo ganhou os documentos de compliance de obra REAIS vistos na aba Hospital SC (CND Federal/Estadual/Municipal, CRF-FGTS, CNDT, comprovantes de pagamento de salario/ferias/13/FGTS, INSS, etc.) — isso responde a pendencia que estava em aberto sobre a lista de documentos de compliance.
A11: ESCOLHA FEITA SOBRE AS DUAS ABAS 'GERAL' DA PLANILHA ANTIGA
A12: A planilha antiga tinha 'GERAL' e 'GERAL (3)' com 66 celulas divergentes entre si (reportado na conferencia anterior). Usei GERAL (3) como fonte porque tem datas reais onde GERAL (sem o (3)) trazia apenas 'INDETERMINADO' — mas isso e uma escolha minha, nao uma confirmacao sua. Se GERAL (sem o (3)) for na verdade a versao correta, aviso que os vencimentos abaixo precisam ser revisados.
A14: COMO LER OS STATUS DE ENVIOS_OBRA_DOCUMENTO
A15: A planilha antiga usava textos livres nas celulas (nem sempre 'OK'). Mantive o texto original na coluna Observacao sempre que ele nao era um simples OK, e preenchi Status_Exigencia com a interpretacao mais proxima:
... A24: 5. Confirmar se o destino final e este Excel ou uma base de dados (Postgres/Supabase).

Sheet Empresas
A1: ID_Empresa | B1: CNPJ | C1: CNPJ_Raiz | D1: Razao_Social | E1: Proprietario | F1: Logradouro | G1: Numero | H1: Bairro | I1: Cidade | J1: UF | K1: CEP | L1: Status | M1: Observacao
A2: EMP-001 | B2: 56.112.624/0001-55 | C2: =LEFT(B2,10) -> 56.112.624 | D2: 56.112.624 ADEILSON FRAGOSO LEAL | E2: ADEILSON FRAGOSO LEAL | F2: R MIGUEL DE LEMOS | G2: 111 | H2: VILA CONTINENTAL | I2: SAO PAULO | J2: SP | K2: 02.616-100 | L2: Ativa
A3: EMP-002 | B3: 60.536.286/0001-56 | C3: =LEFT(B3,10) -> 60.536.286 | D3: 60.536.286 SILVIO SCHURT | E3: SILVIO SCHURT | F3: R LI RUA ANTONIA P. GALESKI | G3: 44 | H3: LUCENA | I3: ITAIOPOLIS | J3: SC | K3: 89.340-000 | L3: Ativa
A4: EMP-003 | B4: 60.555.952/0001-01 | C4: =LEFT(B4,10) -> 60.555.952 | D4: 60.555.952 GABRIEL SCHURT | E4: GABRIEL SCHURT | F4: R JOSE THEODORO RIBEIRO | G4: 1256 | H4: ILHA DA FIGUEIRA | I4: JARAGUA DO SUL | J4: SC | K4: 89258-000 | L4: Ativa
A5: EMP-004 | B5: 45.039.024/0001-92 | C5: =LEFT(B5,10) -> 45.039.024 | D5: AMAZON PESA SERVICOS LTDA | E5: CARMELINA PANTOJA FERREIRA | F5: AV ALCINDO CACELA | G5: 1570 | H5: NAZARE | I5: BELEM | J5: PA | K5: 66.040-020 | L5: Ativa
A6: EMP-005 | B6: 66.166.474/0001-16 | C6: =LEFT(B6,10) -> 66.166.474 | D6: 66.166.474 ANTONIO MARCOS DOS SANTOS | E6: ANTONIO MARCOS DOS SANTOS | F6: LOGRADOUROR DAS UNIOES | G6: 14 | H6: JARDIM MIRAY | I6: ITAQUAQUECETUBA | J6: SP | K6: 08.574-400 | L6: Ativa
A7: EMP-006 | B7: 59.733.299/0001-36 | C7: =LEFT(B7,10) -> 59.733.299 | D7: DHS ELEVADORES LTDA | E7: DANIEL SCHURT | F7: R JAMBO | G7: 116 | H7: AREIAS | I7: TIJUCAS | J7: SC | K7: 88.201-316 | L7: Ativa
A8: EMP-007 | B8: 47.655.284/0001-18 | C8: =LEFT(B8,10) -> 47.655.284 | D8: ERTEX ESCADAS E ESTEIRAS ROLANTES LTDA | E8: ELISEU BALSALOBRE | F8: AV DOS SERTANISTAS | G8: 1525 | H8: JARDIM SANTO ANDRE | I8: SAO PAULO | J8: SP | K8: 08.390-240 | L8: Ativa
A9: EMP-008 | B9: 24.845.692/0006-41 | C9: =LEFT(B9,10) -> 24.845.692 | D9: ESCAMAX MANUTENCAO DE EQUIPAMENTOS DE MOBILIDADE LTDA | E9: DIEGO YUTAKA MAENO | F9: R TERRA ROXA | G9: 231 | H9: CIDADE MAE DO CEU | I9: SAO PAULO | J9: SP | K9: 03.305-010 | L9: Ativa | M9: CNPJ CORRIGIDO — na planilha de origem estava gravado como ' 24.845.692.0006-41'. Confirmar o numero correto.
A10: EMP-009 | B10: 24.845.692/0005-60 | C10: =LEFT(B10,10) -> 24.845.692 | D10: ESCAMAX MANUTENCAO DE EQUIPAMENTOS DE MOBILIDADE LTDA | E10: DIEGO YUTAKA MAENO | F10: R LORD COCHRANE | G10: 66 | H10: BARRA | I10: SALVADOR | J10: BA | K10: 40.140-070 | L10: Ativa
A11: EMP-010 | B11: 24.845.692/0007-22 | C11: =LEFT(B11,10) -> 24.845.692 | D11: ESCAMAX MANUTENCAO DE EQUIPAMENTOS DE MOBILIDADE LTDA | E11: DIEGO YUTAKA MAENO | F11: R SOUZA DUTRA | G11: 1228 | H11: CAPOEIRAS | I11: FLORIANOPOLIS | J11: SC | K11: 88.070-493 | L11: Ativa
A12: EMP-011 | B12: 24.845.692/0001-37 | C12: =LEFT(B12,10) -> 24.845.692 | D12: ESCAMAX MANUTENCAO DE EQUIPAMENTOS DE MOBILIDADE LTDA | E12: DIEGO YUTAKA MAENO | F12: AGUAS CLARAS SUL RUA MACAUBA LT 15/17 | G12: S/N | H12: AGUAS CLARAS | I12: BRASILIA | J12: DF | K12: 71.928-180 | L12: Ativa | M12: Matriz (raiz 24.845.692). Colaboradores da GERAL(3) foram vinculados aqui por padrao — confirmar se deveriam ir para a filial onde atuam.
A13: EMP-012 | B13: 14.253.955/0001-65 | C13: =LEFT(B13,10) -> 14.253.955 | D13: FERNANDO PAVANE MASSEI ELEVADORES | E13: FERNANDO PAVANE MASSEI | F13: R ROSARIO DO SUL | G13: 140 | H13: JARDIM MARINGA | I13: SAO PAULO | J13: SP | K13: 03.523-030 | L13: Ativa
A14: EMP-013 | B14: 50.229.729/0001-02 | C14: =LEFT(B14,10) -> 50.229.729 | D14: LR GRUP ELEVADORES LTDA | E14: LUCAS ALVES DIAS | F14: R NOGUEIRA | G14: 211 | H14: VILA PENTEADO | I14: SAO PAULO | J14: SP | K14: 02.864-060 | L14: Ativa | M14: Na aba Vip Gales de Controle de Documentos.xlsx aparece como 'LR GROUP ELEVADORES' (variacao de grafia) — mesma empresa.
A15: EMP-014 | B15: 36.567.606/0001-50 | C15: =LEFT(B15,10) -> 36.567.606 | D15: LUCIANA MENGALI CARVALHO DA SILVA 32204975869 | E15: LUCIANA MENGALI CARVALHO DA SILVA | F15: R JULIA SCASSIOTI | G15: 125 | H15: JARDIM PARAISO | I15: POCOS DE CALDAS | J15: MG | K15: 37.706-142 | L15: Ativa
A16: EMP-015 | B16: 51.570.098/0001-53 | C16: =LEFT(B16,10) -> 51.570.098 | D16: 51.570.098 LUIZ CARLOS JANUARIO DE LAIA | E16: LUIZ CARLOS JANUARIO DE LAIA | F16: R NOVO ORIENTE DO PIAUI | G16: 777 | H16: VILA SILVIA | I16: SAO PAULO | J16: SP | K16: 03.820-310 | L16: Ativa
A17: EMP-016 | B17: 34.794.316/0001-14 | C17: =LEFT(B17,10) -> 34.794.316 | D17: 34.794.316 LUIS FERNANDO BUENO DE CAMARGO | E17: LUIS FERNANDO BUENO DE CAMARGO | F17: R CANANEIA | G17: 307 | H17: JARDIM PAULISTA | I17: VARZEA PAULISTA | J17: SP | K17: 13.222-070 | L17: Ativa
A18: EMP-017 | B18: 57.708.859/0001-77 | C18: =LEFT(B18,10) -> 57.708.859 | D18: NEXT FLOOR LTDA | E18: FABIO LEANDRO DE FREITAS ASSIS | F18: R FERNANDO SIMAS | G18: 1117 | H18: MERCES | I18: CURITIBA | J18: PR | K18: 80.710-660 | L18: Ativa | M18: Na aba Hospital SC de Controle de Documentos.xlsx aparece como 'NEXTFLOOR' (sem espaco) — mesma empresa.
A19: EMP-018 | B19: 58.520.736/0001-70 | C19: =LEFT(B19,10) -> 58.520.736 | D19: OLIVER ELEVADORES LTDA | E19: LUZIA CRUZ DE OLIVEIRA | F19: TV ROSETA | G19: 26 | H19: LAJEADO | I19: SAO PAULO | J19: SP | K19: 08.452-190 | L19: Ativa
A20: EMP-019 | B20: 12.429.006/0001-68 | C20: =LEFT(B20,10) -> 12.429.006 | D20: RICARDO MANOEL INACIO | E20: RICARDO MANOEL INACIO | F20: R PAULO ARENTINO | G20: 873 | H20: CONJUNTO CITY JARAGUA | I20: SAO PAULO | J20: SP | K20: 02.998-140 | L20: Ativa | M20: Nome fantasia visto na planilha antiga: 'RMI ELEVADORES'.
A21: EMP-020 | B21: 26.708.573/0001-68 | C21: =LEFT(B21,10) -> 26.708.573 | D21: RN SCAL SERVICOS LTDA | E21: LIJOILSON VIDAL DE NEGREIROS | F21: R BELO JARDIM | G21: 123 | H21: PITIMBU | I21: NATAL | J21: RN | K21: 59.068-730 | L21: Ativa | M21: Nome fantasia visto na planilha antiga: 'RN ESCAL'. Proprietario aparece abreviado como 'L. V. Negreiros' na aba Paraguacu.
A22: EMP-021 | B22: A_CONFIRMAR | D22: GUILHERME BITENCOURT DE FREITAS | E22: GUILHERME BITENCOURT DE FREITAS | L22: A_CONFIRMAR | M22: Empresa nova, so encontrada em Controle de Documentos.xlsx (GERAL(3), colaborador 'Guilherme'). CNPJ e endereco nao informados na fonte.
A23: EMP-022 | B23: A_CONFIRMAR | D23: MOSQUITO ESCADAS E ESTEIRAS ROLANTES | L23: A_CONFIRMAR | M23: Empresa nova, so encontrada em Controle de Documentos.xlsx (GERAL(3), colaborador 'Edinaldo dos Santos'). CNPJ e endereco nao informados na fonte. Nome original grafado 'MOSQUITO ESCADAS E ESTERIAS ROLANTES' (provavel erro de digitacao de 'ESTEIRAS') — corrigido aqui.
A24: EMP-023 | B24: A_CONFIRMAR | D24: VDR MONTAGENS LTDA | L24: A_CONFIRMAR | M24: Empresa nova — aparece em Controle de Documentos.xlsx (GERAL(3), colaborador 'Lucas Franco') e na aba Hospital SC (colaborador 'Lucas'). CNPJ e endereco nao informados na fonte.
A25: EMP-024 | B25: A_CONFIRMAR | D25: VERTICAL TECH ELEVADORES LTDA | L25: A_CONFIRMAR | M25: Empresa nova — aparece em Controle de Documentos.xlsx (GERAL(3), colaborador 'Cleiton Navas') e na aba Hospital SC (colaborador 'Cleiton'). Nome original grafado 'VERTICAL TECH ELEVADORS LTDA' (provavel erro de digitacao de 'ELEVADORES') — corrigido aqui. CNPJ e endereco nao informados.
A26: EMP-025 | B26: A_CONFIRMAR | D26: VERTICALPARTS | L26: A_CONFIRMAR | M26: ATENCAO: aparece na GERAL(3) como se fosse uma empresa terceirizada (colaboradores Gesse Batista, Mauricio Sanchez, Vinicius Ramos), grafada tambem como 'VERTICAPARTS' (erro de digitacao). Pode ser a propria VerticalParts (empresa contratante), nao uma subcontratada — CONFIRMAR antes de tratar como empresa instaladora terceirizada.

Sheet Colaboradores
A1: ID_Colaborador | B1: CPF | C1: RG | D1: CNH | E1: Nome_Completo | F1: Tipo_Vinculo | G1: Logradouro | H1: Numero | I1: Bairro | J1: Cidade | K1: UF | L1: CEP | M1: Status | N1: Observacao
A2: COL-001 | D2: 7123679432 | E2: ADEILSON FRAGOSO LEAL | M2: Ativo | N2: CNH gravada como numero na planilha original (perde zero a esquerda) — confirmar os 11 digitos corretos.
A3: COL-002 | D3: 00796038480 | E3: SILVIO SCHURT | G3: R LI RUA ANTONIA P. GALESKI | H3: 44 | I3: LUCENA | J3: ITAIOPOLIS | K3: SC | L3: 89.340-000 | M3: Ativo
A4: COL-003 | D4: 07631999812 | E4: GABRIEL SCHURT | G4: R LINGUADO | H4: 381 | I4: SANTA LUZIA | J4: TIJUCAS | K4: SC | L4: 88200-000 | M4: Ativo
A5: COL-004 | D5: 01765244690 | E5: ANTONIO DA SILVA PALACIOS | M5: Ativo
A6: COL-005 | D6: 05353694666 | E6: SERGIO MARCOS LEONCIO | M6: Ativo
A7: COL-006 | D7: 05140368402 | E7: SIDNEY ALVES DOS SANTOS | M7: Ativo
A8: COL-007 | C8: 20.113.969-8 | E8: ANTONIO MARCOS DOS SANTOS | G8: R DAS UNIOES | H8: 14 | I8: JARDIM MIRAY | J8: ITAQUAQUECETUBA | K8: SP | L8: 08574-400 | M8: Ativo
A9: COL-008 | D9: 05753158046 | E9: DANIEL SCHURT | G9: R JAMBO | H9: 116 | I9: AREIAS | J9: TIJUCAS | K9: SC | L9: 88.201-316 | M9: Ativo
A10: COL-009 | D10: 05071494068 | E10: ELISEU BALSALOBRE | M10: Ativo
A11: COL-010 | B11: 454.718.548-45 | E11: ERNANDO LOPES VIANA DA SILVA | M11: Ativo | N11: Na planilha original o RG estava preenchido com o mesmo valor do CPF (454.718.548-45) — RG real fica em aberto ate confirmar.
A12: COL-011 | D12: 075759506685 | E12: ISMAEL BEREZZA LOPES | M12: Ativo | N12: CNH com 12 digitos na planilha original — CNH valida tem 11 digitos, provavel erro de digitacao a confirmar.
A13: COL-012 | D13: 03932810303 | E13: FERNANDO PAVANE MASSEI | M13: Ativo
A14: COL-013 | D14: 05015245137 | E14: RICARDO SEVERINO DA SILVA | M14: Ativo
A15: COL-014 | D15: 04543171125 | E15: CARLOS ALBERTO CARVALHO DA SILVA | M15: Ativo
A16: COL-015 | C16: 22027609 | D16: 07943131410 | E16: KAUA WENDEL MENGALI DOMINGOS | M16: Ativo
A17: COL-016 | D17: 02793998701 | E17: LUIZ CARLOS JANUARIO DE LAIA | M17: Ativo
A18: COL-017 | D18: 04401142303 | E18: LUIS FERNANDO BUENO DE CAMARGO | M18: Ativo
A19: COL-018 | D19: 06134503425 | E19: FABIO LEANDRO DE FREITAS ASSIS | M19: Ativo
A20: COL-019 | B20: 298.440.068-30 | D20: 01639658250 | E20: ANDERSON DA SILVA | M20: Ativo | N20: Na planilha original o RG estava preenchido com o mesmo valor do CPF (298.440.068-30) — RG real fica em aberto ate confirmar.
A21: COL-020 | D21: 07376931649 | E21: WALISON TANDI AZEVEDO DE OLIVEIRA MELO | M21: Ativo
A22: COL-021 | E22: AGOSTINHO GONCALVES CORDEIRO | M22: Ativo
A23: COL-022 | E23: FRANCISCO DE ASSIS SANTOS NASCIMENTO | M23: Ativo
A24: COL-023 | E24: JOAO PAULO BATISTA DOS SANTOS | M24: Ativo
A25: COL-024 | E25: RICARDO MANOEL INACIO | M25: Ativo
A26: COL-025 | E26: SAMUEL VICENTE NAZARO DA SILVA | M26: Ativo
A27: COL-026 | D27: 04062677057 | E27: JOAO MARIA CANDIDO DE OLIVEIRA | M27: Ativo
A28: COL-027 | D28: 02574407004 | E28: MANOEL SEVERO NETO | M28: Ativo
A29: COL-028 | D29: 05946844447 | E29: RAFAEL PEREIRA DE LIMA | M29: Ativo
A30: COL-029 | E30: ANDERSON CARLOS DE SOUSA DA SILVA | M30: Ativo
A31: COL-030 | D31: 05465304836 | E31: AVANY MAIA DOS REIS | M31: Ativo
A32: COL-031 | D32: 07245077336 | E32: BELION FELIPE FERNANDES CORREIA | M32: Ativo
A33: COL-032 | D33: 04190355647 | E33: CARLOS JORGE DA SILVA | M33: Ativo
A34: COL-033 | D34: 05313891003 | E34: DANIEL APARECIDO DOS REIS FELICIANO | M34: Ativo
A35: COL-034 | E35: ELSON RICARDO BATISTA PINTO | M35: Ativo
A36: COL-035 | D36: 05941652100 | E36: EVERTON VICTOR SANTOS PEREIRA | M36: Ativo
A37: COL-036 | D37: 06392033495 | E37: GUSTAVO RODRIGUES DE AZEVEDO | M37: Ativo
A38: COL-037 | E38: MARTHOS VINICIO FERREIRA RAMOS | M38: Ativo
A39: COL-038 | D39: 04845246604 | E39: MATHEUS MOTA RIBEIRO | M39: Ativo
A40: COL-039 | E40: PAULO CESAR ALVES DA SILVA | M40: Ativo | N40: Na planilha original havia '62193555397' no campo RG — parece um CPF (11 digitos), nao um RG. Confirmar RG e CPF reais.
A41: COL-040 | D41: 07767534150 | E41: YOANDERSON COSTA DOS SANTOS | M41: Ativo
A42: COL-041 | E42: GABRIEL SCHURT (proprietario) | M42: A_CONFIRMAR | N42: NOVO — nao existia em Planilha Organizar (1).xlsx. Encontrado na aba Hospital SC de Controle de Documentos.xlsx (coluna da empresa 60.555.952 GABRIEL SCHURT). Provavelmente proprietario = colaborador principal desta empresa individual.
A43: COL-042 | E43: MARCIO MARTINS | M43: A_CONFIRMAR | N43: NOVO — encontrado em Controle de Documentos.xlsx (GERAL(3), empresa 'LUIS FERNANDO BUENO DE CAMARGO'). Sem CPF/RG/CNH informados.
A44: COL-043 | E44: EDINALDO DOS SANTOS | M44: A_CONFIRMAR | N44: NOVO — encontrado em Controle de Documentos.xlsx (GERAL(3), empresa 'MOSQUITO ESCADAS E ESTEIRAS ROLANTES'). Sem CPF/RG/CNH informados.
A45: COL-044 | E45: GUILHERME BITENCOURT DE FREITAS | M45: A_CONFIRMAR | N45: NOVO — colaborador e nome da empresa individual coincidem (provavel proprietario). Sem CPF/RG/CNH informados.
A46: COL-045 | E46: DINHO | M46: A_CONFIRMAR | N46: NOVO — encontrado em Controle de Documentos.xlsx (GERAL(3), empresa RN ESCAL). Provavel apelido — nome completo a confirmar.
A47: COL-046 | E47: PAULO SILVA | M47: A_CONFIRMAR | N47: NOVO — encontrado em Controle de Documentos.xlsx (GERAL(3), empresa RN ESCAL) e na aba Paraguacu (mesma pessoa).
A48: COL-047 | E48: DENILSON ABREU | M48: A_CONFIRMAR | N48: NOVO — encontrado tambem na aba Paraguacu (mesma pessoa, RN Escal/RN Scal atua nessa obra).
A49: COL-048 | E49: JOSUE SANTOS | M49: A_CONFIRMAR | N49: NOVO — encontrado tambem na aba Paraguacu (mesma pessoa).
A50: COL-049 | E50: MARCELO SANTOS | M50: A_CONFIRMAR | N50: NOVO — encontrado tambem na aba Paraguacu (mesma pessoa).
A51: COL-050 | E51: LUCAS FRANCO | M51: A_CONFIRMAR | N51: NOVO — encontrado em Controle de Documentos.xlsx (GERAL(3), empresa VDR MONTAGENS LTDA) e na aba Hospital SC (mesma pessoa, 'Lucas').
A52: COL-051 | E52: CLEITON NAVAS | M52: A_CONFIRMAR | N52: NOVO — encontrado em Controle de Documentos.xlsx (GERAL(3), empresa VERTICAL TECH ELEVADORES LTDA) e na aba Hospital SC (mesma pessoa, 'Cleiton').
A53: COL-052 | E53: GESSE BATISTA | M53: A_CONFIRMAR | N53: NOVO — ver observacao na aba Empresas sobre 'VERTICALPARTS' possivelmente ser a propria contratante, nao uma terceirizada.
... A55: COL-054 | E55: VINICIUS RAMOS | M55: A_CONFIRMAR | N55: NOVO — idem. Nao havia nenhum documento preenchido para esta pessoa na fonte.

Sheet Colaborador_Empresa
A1: ID_Vinculo | B1: ID_Colaborador | C1: Nome_Colaborador | D1: ID_Empresa | E1: Razao_Social_Empresa | F1: Funcao | G1: Data_Inicio | H1: Data_Fim | I1: Vinculo_Principal
A2: VIN-001 | B2: COL-001 | C2: =IFERROR(INDEX(Colaboradores!$E:$E,MATCH(B2,Colaboradores!$A:$A,0)),"") -> ADEILSON FRAGOSO LEAL | D2: EMP-001 | E2: =IFERROR(INDEX(Empresas!$D:$D,MATCH(D2,Empresas!$A:$A,0)),"") -> 56.112.624 ADEILSON FRAGOSO LEAL | I2: SIM
A3: VIN-002 | B3: COL-002 | C3: =IFERROR(INDEX(Colaboradores!$E:$E,MATCH(B3,Colaboradores!$A:$A,0)),"") -> SILVIO SCHURT | D3: EMP-002 | E3: =IFERROR(INDEX(Empresas!$D:$D,MATCH(D3,Empresas!$A:$A,0)),"") -> 60.536.286 SILVIO SCHURT | I3: SIM
A4: VIN-003 | B4: COL-003 | C4: =IFERROR(INDEX(Colaboradores!$E:$E,MATCH(B4,Colaboradores!$A:$A,0)),"") -> GABRIEL SCHURT | D4: EMP-003 | E4: =IFERROR(INDEX(Empresas!$D:$D,MATCH(D4,Empresas!$A:$A,0)),"") -> 60.555.952 GABRIEL SCHURT | I4: SIM
A5: VIN-004 | B5: COL-004 | C5: =IFERROR(INDEX(Colaboradores!$E:$E,MATCH(B5,Colaboradores!$A:$A,0)),"") -> ANTONIO DA SILVA PALACIOS | D5: EMP-004 | E5: =IFERROR(INDEX(Empresas!$D:$D,MATCH(D5,Empresas!$A:$A,0)),"") -> AMAZON PESA SERVICOS LTDA | I5: SIM
A6: VIN-005 | B6: COL-005 | C6: =IFERROR(INDEX(Colaboradores!$E:$E,MATCH(B6,Colaboradores!$A:$A,0)),"") -> SERGIO MARCOS LEONCIO | D6: EMP-004 | E6: =IFERROR(INDEX(Empresas!$D:$D,MATCH(D6,Empresas!$A:$A,0)),"") -> AMAZON PESA SERVICOS LTDA | I6: SIM
A7: VIN-006 | B7: COL-006 | C7: =IFERROR(INDEX(Colaboradores!$E:$E,MATCH(B7,Colaboradores!$A:$A,0)),"") -> SIDNEY ALVES DOS SANTOS | D7: EMP-004 | E7: =IFERROR(INDEX(Empresas!$D:$D,MATCH(D7,Empresas!$A:$A,0)),"") -> AMAZON PESA SERVICOS LTDA | I7: SIM
A8: VIN-007 | B8: COL-007 | C8: =IFERROR(INDEX(Colaboradores!$E:$E,MATCH(B8,Colaboradores!$A:$A,0)),"") -> ANTONIO MARCOS DOS SANTOS | D8: EMP-005 | E8: =IFERROR(INDEX(Empresas!$D:$D,MATCH(D8,Empresas!$A:$A,0)),"") -> 66.166.474 ANTONIO MARCOS DOS SANTOS | I8: SIM
A9: VIN-008 | B9: COL-008 | C9: =IFERROR(INDEX(Colaboradores!$E:$E,MATCH(B9,Colaboradores!$A:$A,0)),"") -> DANIEL SCHURT | D9: EMP-006 | E9: =IFERROR(INDEX(Empresas!$D:$D,MATCH(D9,Empresas!$A:$A,0)),"") -> DHS ELEVADORES LTDA | I9: SIM
A10: VIN-009 | B10: COL-009 | C10: =IFERROR(INDEX(Colaboradores!$E:$E,MATCH(B10,Colaboradores!$A:$A,0)),"") -> ELISEU BALSALOBRE | D10: EMP-007 | E10: =IFERROR(INDEX(Empresas!$D:$D,MATCH(D10,Empresas!$A:$A,0)),"") -> ERTEX ESCADAS E ESTEIRAS ROLANTES LTDA | I10: SIM
A11: VIN-010 | B11: COL-010 | C11: =IFERROR(INDEX(Colaboradores!$E:$E,MATCH(B11,Colaboradores!$A:$A,0)),"") -> ERNANDO LOPES VIANA DA SILVA | D11: EMP-007 | E11: =IFERROR(INDEX(Empresas!$D:$D,MATCH(D11,Empresas!$A:$A,0)),"") -> ERTEX ESCADAS E ESTEIRAS ROLANTES LTDA | I11: SIM
A12: VIN-011 | B12: COL-011 | C12: =IFERROR(INDEX(Colaboradores!$E:$E,MATCH(B12,Colaboradores!$A:$A,0)),"") -> ISMAEL BEREZZA LOPES | D12: EMP-007 | E12: =IFERROR(INDEX(Empresas!$D:$D,MATCH(D12,Empresas!$A:$A,0)),"") -> ERTEX ESCADAS E ESTEIRAS ROLANTES LTDA | I12: SIM
A13: VIN-012 | B13: COL-012 | C13: =IFERROR(INDEX(Colaboradores!$E:$E,MATCH(B13,Colaboradores!$A:$A,0)),"") -> FERNANDO PAVANE MASSEI | D13: EMP-012 | E13: =IFERROR(INDEX(Empresas!$D:$D,MATCH(D13,Empresas!$A:$A,0)),"") -> FERNANDO PAVANE MASSEI ELEVADORES | I13: SIM
... A55: VIN-054 | B55: COL-054 | C55: =IFERROR(INDEX(Colaboradores!$E:$E,MATCH(B55,Colaboradores!$A:$A,0)),"") -> VINICIUS RAMOS | D55: EMP-025 | E55: =IFERROR(INDEX(Empresas!$D:$D,MATCH(D55,Empresas!$A:$A,0)),"") -> VERTICALPARTS | I55: SIM

Sheet Especialidades
A1: ID_Especialidade | B1: Nome | C1: Observacao
A2: ESP-01 | B2: Elevador | C2: Confirmado pela obra Metro SP ('DESMONTAGEM DE 2 ELEVADORES'). Lista completa a confirmar com Gelson.
A3: ESP-02 | B3: Escada Rolante
A4: ESP-03 | B4: Esteira Rolante

Sheet Obras
A1: ID_Obra | B1: Nome | C1: Cliente_Construtora | D1: Endereco | E1: Status | F1: Data_Inicio_Prevista | G1: Data_Inicio_Real | H1: Data_Fim_Prevista | I1: Data_Fim_Real | J1: Observacao
A2: OBR-001 | B2: Metro SP | E2: A_CONFIRMAR | J2: Obra de desmontagem de 2 elevadores, executada pela Oliver Elevadores LTDA.
A3: OBR-002 | B3: Metro BH | E3: A_CONFIRMAR | J3: Equipe ESCAMAX (matriz) atuando.
A4: OBR-003 | B4: Hospital SC | E4: A_CONFIRMAR | J4: 6 empresas diferentes alocadas — ver Obra_Empresa.
A5: OBR-004 | B5: Paraguaçu | E5: A_CONFIRMAR | J5: Equipe RN SCAL / RN Escal atuando.
A6: OBR-005 | B6: Vip Gales | E6: A_CONFIRMAR | J6: Equipe LR Grup Elevadores atuando.
A7: OBR-006 | B7: Goiabeiras | E7: A_CONFIRMAR | J7: Aba totalmente vazia na planilha antiga — nenhuma empresa/colaborador confirmado ainda.

Sheet Obra_Empresa
A1: ID_Alocacao | B1: ID_Obra | C1: Nome_Obra | D1: ID_Empresa | E1: Nome_Empresa | F1: Papel | G1: Observacao
A2: ALOC-001 | B2: OBR-003 | C2: =IFERROR(INDEX(Obras!$B:$B,MATCH(B2,Obras!$A:$A,0)),"") -> Hospital SC | D2: EMP-002 | E2: =IFERROR(INDEX(Empresas!$D:$D,MATCH(D2,Empresas!$A:$A,0)),"") -> 60.536.286 SILVIO SCHURT | F2: A_CONFIRMAR | G2: Alocacao inferida a partir dos documentos enviados na aba desta obra em Controle de Documentos.xlsx.
A3: ALOC-002 | B3: OBR-003 | C3: =IFERROR(INDEX(Obras!$B:$B,MATCH(B3,Obras!$A:$A,0)),"") -> Hospital SC | D3: EMP-003 | E3: =IFERROR(INDEX(Empresas!$D:$D,MATCH(D3,Empresas!$A:$A,0)),"") -> 60.555.952 GABRIEL SCHURT | F3: A_CONFIRMAR | G3: Alocacao inferida a partir dos documentos enviados na aba desta obra em Controle de Documentos.xlsx.
A4: ALOC-003 | B4: OBR-003 | C4: =IFERROR(INDEX(Obras!$B:$B,MATCH(B4,Obras!$A:$A,0)),"") -> Hospital SC | D4: EMP-006 | E4: =IFERROR(INDEX(Empresas!$D:$D,MATCH(D4,Empresas!$A:$A,0)),"") -> DHS ELEVADORES LTDA | F4: A_CONFIRMAR | G4: Alocacao inferida a partir dos documentos enviados na aba desta obra em Controle de Documentos.xlsx.
A5: ALOC-004 | B5: OBR-003 | C5: =IFERROR(INDEX(Obras!$B:$B,MATCH(B5,Obras!$A:$A,0)),"") -> Hospital SC | D5: EMP-017 | E5: =IFERROR(INDEX(Empresas!$D:$D,MATCH(D5,Empresas!$A:$A,0)),"") -> NEXT FLOOR LTDA | F5: A_CONFIRMAR | G5: Alocacao inferida a partir dos documentos enviados na aba desta obra em Controle de Documentos.xlsx.
A6: ALOC-005 | B6: OBR-003 | C6: =IFERROR(INDEX(Obras!$B:$B,MATCH(B6,Obras!$A:$A,0)),"") -> Hospital SC | D6: EMP-023 | E6: =IFERROR(INDEX(Empresas!$D:$D,MATCH(D6,Empresas!$A:$A,0)),"") -> VDR MONTAGENS LTDA | F6: A_CONFIRMAR | G6: Alocacao inferida a partir dos documentos enviados na aba desta obra em Controle de Documentos.xlsx.
A7: ALOC-006 | B7: OBR-003 | C7: =IFERROR(INDEX(Obras!$B:$B,MATCH(B7,Obras!$A:$A,0)),"") -> Hospital SC | D7: EMP-024 | E7: =IFERROR(INDEX(Empresas!$D:$D,MATCH(D7,Empresas!$A:$A,0)),"") -> VERTICAL TECH ELEVADORES LTDA | F7: A_CONFIRMAR | G7: Alocacao inferida a partir dos documentos enviados na aba desta obra em Controle de Documentos.xlsx.
A8: ALOC-007 | B8: OBR-002 | C8: =IFERROR(INDEX(Obras!$B:$B,MATCH(B8,Obras!$A:$A,0)),"") -> Metro BH | D8: EMP-011 | E8: =IFERROR(INDEX(Empresas!$D:$D,MATCH(D8,Empresas!$A:$A,0)),"") -> ESCAMAX MANUTENCAO DE EQUIPAMENTOS DE MOBILIDADE LTDA | F8: A_CONFIRMAR | G8: Alocacao inferida a partir dos documentos enviados na aba desta obra em Controle de Documentos.xlsx.
A9: ALOC-008 | B9: OBR-001 | C9: =IFERROR(INDEX(Obras!$B:$B,MATCH(B9,Obras!$A:$A,0)),"") -> Metro SP | D9: EMP-018 | E9: =IFERROR(INDEX(Empresas!$D:$D,MATCH(D9,Empresas!$A:$A,0)),"") -> OLIVER ELEVADORES LTDA | F9: A_CONFIRMAR | G9: Alocacao inferida a partir dos documentos enviados na aba desta obra em Controle de Documentos.xlsx.
A10: ALOC-009 | B10: OBR-004 | C10: =IFERROR(INDEX(Obras!$B:$B,MATCH(B10,Obras!$A:$A,0)),"") -> Paraguaçu | D10: EMP-020 | E10: =IFERROR(INDEX(Empresas!$D:$D,MATCH(D10,Empresas!$A:$A,0)),"") -> RN SCAL SERVICOS LTDA | F10: A_CONFIRMAR | G10: Alocacao inferida a partir dos documentos enviados na aba desta obra em Controle de Documentos.xlsx.
A11: ALOC-010 | B11: OBR-005 | C11: =IFERROR(INDEX(Obras!$B:$B,MATCH(B11,Obras!$A:$A,0)),"") -> Vip Gales | D11: EMP-013 | E11: =IFERROR(INDEX(Empresas!$D:$D,MATCH(D11,Empresas!$A:$A,0)),"") -> LR GRUP ELEVADORES LTDA | F11: A_CONFIRMAR | G11: Alocacao inferida a partir dos documentos enviados na aba desta obra em Controle de Documentos.xlsx.

Sheet Especialidade_Obra_Empresa
A1: ID | B1: ID_Alocacao | C1: Nome_Obra_Empresa | D1: ID_Especialidade | E1: Nome_Especialidade | F1: Observacao
A2: ESPOE-001 | B2: ALOC-008 | C2: =IFERROR(INDEX(Obra_Empresa!$E:$E,MATCH(B2,Obra_Empresa!$A:$A,0))&" / "&INDEX(Obra_Empresa!$C:$C,MATCH(B2,Obra_Empresa!$A:$A,0)),"") -> OLIVER ELEVADORES LTDA / Metro SP | D2: ESP-01 | E2: =IFERROR(INDEX(Especialidades!$B:$B,MATCH(D2,Especialidades!$A:$A,0)),"") -> Elevador | F2: Unica associacao confirmada pela fonte ('DESMONTAGEM DE 2 ELEVADORES' na aba Metro SP).

Sheet Doc_Catalogo
A1: ID_Documento | B1: Nome | C1: Escopo | D1: Periodicidade | E1: Obrigatorio | F1: Origem_na_planilha_antiga | G1: Observacao
A2: DOC-001 | B2: RG | C2: colaborador | D2: decenal | E2: SIM | F2: Controle de Documentos.xlsx (GERAL) | G2: Periodicidade herdada do titulo da coluna na planilha antiga (Controle de Documentos.xlsx) — nao foi conferida contra a norma vigente do MTE. Confirmar antes de usar em alerta automatico de vencimento.
A3: DOC-002 | B3: CPF | C3: colaborador | D3: indeterminado | E3: SIM | F3: Controle de Documentos.xlsx (GERAL)
A4: DOC-003 | B4: CNH | C4: colaborador | D4: decenal | E4: NAO | F4: Controle de Documentos.xlsx (GERAL) | G4: Periodicidade herdada do titulo da coluna na planilha antiga (Controle de Documentos.xlsx) — nao foi conferida contra a norma vigente do MTE. Confirmar antes de usar em alerta automatico de vencimento. CNH pode vencer em 5 ou 10 anos dependendo da idade do condutor — confirmar regra.
A5: DOC-004 | B5: ASO | C5: colaborador | D5: a_confirmar | E5: SIM | F5: Controle de Documentos.xlsx (GERAL) | G5: As duas abas GERAL da planilha antiga divergiam entre data real e 'INDETERMINADO' para o mesmo colaborador — usei GERAL(3) como fonte (ver Leia-me).
A6: DOC-005 | B6: CNPJ (situacao cadastral) | C6: empresa | D6: indeterminado | E6: SIM | F6: Controle de Documentos.xlsx (GERAL)
A7: DOC-006 | B7: Certificado da NR01 — Empresa | C7: empresa | D7: vinculado_pgr | E7: SIM | F7: Controle de Documentos.xlsx / Planilha Organizar (Doc_Empresa) | G7: Renovada junto da PGR — nao tem vencimento proprio.
A8: DOC-007 | B8: Certificado da NR01 — Colaborador | C8: colaborador | D8: vinculado_pgr | E8: SIM | F8: Controle de Documentos.xlsx / Planilha Organizar (Doc_Funcionario) | G8: Renovada junto da PGR — nao tem vencimento proprio.
A9: DOC-008 | B9: Certificado da NR06 — Empresa | C9: empresa | D9: anual | E9: SIM | F9: Controle de Documentos.xlsx / Planilha Organizar (Doc_Empresa) | G9: Periodicidade herdada do titulo da coluna na planilha antiga (Controle de Documentos.xlsx) — nao foi conferida contra a norma vigente do MTE. Confirmar antes de usar em alerta automatico de vencimento.
A10: DOC-009 | B10: Certificado da NR06 — Colaborador | C10: colaborador | D10: anual | E10: SIM | F10: Controle de Documentos.xlsx / Planilha Organizar (Doc_Funcionario) | G10: Periodicidade herdada do titulo da coluna na planilha antiga (Controle de Documentos.xlsx) — nao foi conferida contra a norma vigente do MTE. Confirmar antes de usar em alerta automatico de vencimento.
A11: DOC-010 | B11: Certificado da NR10 — Empresa | C11: empresa | D11: bienal | E11: SIM | F11: Controle de Documentos.xlsx / Planilha Organizar (Doc_Empresa) | G11: Periodicidade herdada do titulo da coluna na planilha antiga (Controle de Documentos.xlsx) — nao foi conferida contra a norma vigente do MTE. Confirmar antes de usar em alerta automatico de vencimento.
A12: DOC-011 | B12: Certificado da NR10 — Colaborador | C12: colaborador | D12: bienal | E12: SIM | F12: Controle de Documentos.xlsx / Planilha Organizar (Doc_Funcionario) | G12: Periodicidade herdada do titulo da coluna na planilha antiga (Controle de Documentos.xlsx) — nao foi conferida contra a norma vigente do MTE. Confirmar antes de usar em alerta automatico de vencimento.
A13: DOC-012 | B13: Carta de anuencia (NR10) — Empresa | C13: empresa | D13: a_confirmar | E13: SIM | F13: Controle de Documentos.xlsx / Planilha Organizar (Doc_Empresa) | G13: Planilha antiga nao trazia periodicidade para este documento — confirmar com Gelson/Felipe.
A14: DOC-013 | B14: Carta de anuencia (NR10) — Colaborador | C14: colaborador | D14: a_confirmar | E14: SIM | F14: Controle de Documentos.xlsx / Planilha Organizar (Doc_Funcionario) | G14: Planilha antiga nao trazia periodicidade para este documento — confirmar com Gelson/Felipe.
A15: DOC-014 | B15: Certificado da NR11 — Empresa | C15: empresa | D15: anual | E15: SIM | F15: Controle de Documentos.xlsx / Planilha Organizar (Doc_Empresa) | G15: Periodicidade herdada do titulo da coluna na planilha antiga (Controle de Documentos.xlsx) — nao foi conferida contra a norma vigente do MTE. Confirmar antes de usar em alerta automatico de vencimento.
A16: DOC-015 | B16: Certificado da NR11 — Colaborador | C16: colaborador | D16: anual | E16: SIM | F16: Controle de Documentos.xlsx / Planilha Organizar (Doc_Funcionario) | G16: Periodicidade herdada do titulo da coluna na planilha antiga (Controle de Documentos.xlsx) — nao foi conferida contra a norma vigente do MTE. Confirmar antes de usar em alerta automatico de vencimento.
A17: DOC-016 | B17: Certificado da NR12 — Empresa | C17: empresa | D17: bienal | E17: SIM | F17: Controle de Documentos.xlsx / Planilha Organizar (Doc_Empresa) | G17: Periodicidade herdada do titulo da coluna na planilha antiga (Controle de Documentos.xlsx) — nao foi conferida contra a norma vigente do MTE. Confirmar antes de usar em alerta automatico de vencimento.
A18: DOC-017 | B18: Certificado da NR12 — Colaborador | C18: colaborador | D18: bienal | E18: SIM | F18: Controle de Documentos.xlsx / Planilha Organizar (Doc_Funcionario) | G18: Periodicidade herdada do titulo da coluna na planilha antiga (Controle de Documentos.xlsx) — nao foi conferida contra a norma vigente do MTE. Confirmar antes de usar em alerta automatico de vencimento.
... A51: DOC-050 | B51: PCMSO | C51: empresa | D51: a_confirmar | E51: SIM | F51: Controle de Documentos.xlsx (abas por obra) | G51: Planilha antiga nao trazia periodicidade para este documento — confirmar com Gelson/Felipe.
A52: DOC-051 | B52: Contrato Social | C52: empresa | D52: indeterminado | E52: SIM | F52: Metro SP
A53: DOC-052 | B53: Inscricao Estadual / Municipal | C53: empresa | D53: indeterminado | E53: NAO | F53: Metro SP | G53: Nem toda empresa se aplica.
A54: DOC-053 | B54: APR — Analise Preliminar de Risco | C54: empresa | D54: a_confirmar | E54: NAO | F54: Metro SP | G54: Planilha antiga nao trazia periodicidade para este documento — confirmar com Gelson/Felipe.
A55: DOC-054 | B55: DARF | C55: empresa | D55: mensal | E55: NAO | F55: Hospital SC | G55: Planilha antiga nao trazia periodicidade para este documento — confirmar com Gelson/Felipe.
A56: DOC-055 | B56: DCTF | C56: empresa | D56: mensal | E56: NAO | F56: Hospital SC | G56: Planilha antiga nao trazia periodicidade para este documento — confirmar com Gelson/Felipe.
A57: DOC-056 | B57: Curso de soldador para atividades com solda | C57: colaborador | D57: a_confirmar | E57: NAO | F57: Paraguacu | G57: Aplica-se apenas a quem solda.
A58: DOC-057 | B58: Curso de direcao defensiva para motoristas | C58: colaborador | D58: a_confirmar | E58: NAO | F58: Paraguacu | G58: Aplica-se apenas a quem dirige veiculo da empresa.
A59: DOC-058 | B59: Contrato de prestacao de servicos entre tomador e empreiteiro | C59: obra_compliance | D59: evento_unico | E59: SIM | F59: Hospital SC
A60: DOC-059 | B60: Livro de Inspecao do canteiro de Obras | C60: obra_compliance | D60: a_confirmar | E60: SIM | F60: Hospital SC | G60: Planilha antiga nao trazia periodicidade para este documento — confirmar com Gelson/Felipe.
A61: DOC-060 | B61: Inventario de riscos da obra | C61: obra_compliance | D61: a_confirmar | E61: SIM | F61: Hospital SC | G61: Planilha antiga nao trazia periodicidade para este documento — confirmar com Gelson/Felipe.
A62: DOC-061 | B62: Alvara de Localizacao e Funcionamento (Prefeitura) | C62: obra_compliance | D62: indeterminado | E62: NAO | F62: Hospital SC | G62: Nao se aplica a MEI, segundo a fonte.
A63: DOC-062 | B63: Documentos pessoais do empreiteiro e socios | C63: obra_compliance | D63: indeterminado | E63: SIM | F63: Hospital SC
A64: DOC-063 | B64: Comprovante de endereco do empreiteiro e socios | C64: obra_compliance | D64: indeterminado | E64: SIM | F64: Hospital SC
A65: DOC-064 | B65: Comprovante mensal de pagamento do Seguro de Vida dos Trabalhadores | C65: obra_compliance | D65: mensal | E65: SIM | F65: Hospital SC
A66: DOC-065 | B66: Certidao de feitos trabalhistas do foro da sede do empreiteiro | C66: obra_compliance | D66: a_confirmar | E66: NAO | F66: Hospital SC | G66: Planilha antiga nao trazia periodicidade para este documento — confirmar com Gelson/Felipe.
A67: DOC-066 | B67: Declaracao Treinamento do SECONCI | C67: obra_compliance | D67: a_confirmar | E67: NAO | F67: Hospital SC | G67: Planilha antiga nao trazia periodicidade para este documento — confirmar com Gelson/Felipe.
A68: DOC-067 | B68: Declaracao da contabilidade do empreiteiro | C68: obra_compliance | D68: a_confirmar | E68: SIM | F68: Hospital SC | G68: Planilha antiga nao trazia periodicidade para este documento — confirmar com Gelson/Felipe.
A69: DOC-068 | B69: Comprovante de pagamento de salarios | C69: obra_compliance | D69: mensal | E69: SIM | F69: Hospital SC
A70: DOC-069 | B70: Comprovante de pagamento de ferias | C70: obra_compliance | D70: evento_unico | E70: SIM | F70: Hospital SC
A71: DOC-070 | B71: Comprovante de pagamento de 13o salario | C71: obra_compliance | D71: evento_unico | E71: SIM | F71: Hospital SC
A72: DOC-071 | B72: Comprovante de pagamento de FGTS | C72: obra_compliance | D72: mensal | E72: SIM | F72: Hospital SC
A73: DOC-072 | B73: Comprovante de recolhimento de INSS | C73: obra_compliance | D73: mensal | E73: SIM | F73: Hospital SC
A74: DOC-073 | B74: CND Federal (Receita Federal) | C74: obra_compliance | D74: a_confirmar | E74: SIM | F74: Hospital SC | G74: Planilha antiga nao trazia periodicidade para este documento — confirmar com Gelson/Felipe.
A75: DOC-074 | B75: CND Estadual | C75: obra_compliance | D75: a_confirmar | E75: SIM | F75: Hospital SC | G75: Planilha antiga nao trazia periodicidade para este documento — confirmar com Gelson/Felipe.
A76: DOC-075 | B76: CND Municipal | C76: obra_compliance | D76: a_confirmar | E76: SIM | F76: Hospital SC | G76: Planilha antiga nao trazia periodicidade para este documento — confirmar com Gelson/Felipe.
A77: DOC-076 | B77: CRF — Certificado de Regularidade do FGTS | C77: obra_compliance | D77: a_confirmar | E77: SIM | F77: Hospital SC | G77: Planilha antiga nao trazia periodicidade para este documento — confirmar com Gelson/Felipe.
A78: DOC-077 | B78: CNDT — Certidao Negativa de Debitos Trabalhistas | C78: obra_compliance | D78: a_confirmar | E78: SIM | F78: Hospital SC | G78: Planilha antiga nao trazia periodicidade para este documento — confirmar com Gelson/Felipe.
A79: DOC-078 | B79: Declaracao de fornecimento de refeicao | C79: obra_compliance | D79: a_confirmar | E79: NAO | F79: Paraguacu | G79: Planilha antiga nao trazia periodicidade para este documento — confirmar com Gelson/Felipe.
A80: DOC-079 | B80: Designado da CIPA (obras com mais de 5 funcionarios) | C80: obra_compliance | D80: a_confirmar | E80: NAO | F80: Vip Gales / Goiabeiras | G80: Planilha antiga nao trazia periodicidade para este documento — confirmar com Gelson/Felipe.

Sheet Docs_Empresa
A1: ID_Registro | B1: ID_Empresa | C1: Nome_Empresa | D1: ID_Documento | E1: Nome_Documento | F1: Data_Emissao | G1: Data_Vencimento | H1: Status | I1: Arquivo_Link | J1: Observacao
A2: REG-0001 | B2: EMP-001 | C2: =IFERROR(INDEX(Empresas!$D:$D,MATCH(B2,Empresas!$A:$A,0)),"") -> 56.112.624 ADEILSON FRAGOSO LEAL | D2: DOC-005 | E2: =IFERROR(INDEX(Doc_Catalogo!$B:$B,MATCH(D2,Doc_Catalogo!$A:$A,0)),"") -> CNPJ (situacao cadastral) | H2: =IF(G2="","N/A",IF(G2<TODAY(),"VENCIDO",IF(G2<=TODAY()+30,"VENCENDO","VALIDO"))) -> N/A | J2: Marcado como INDETERMINADO na planilha antiga (documento existe, sem data de vencimento fixa).
A3: REG-0002 | B3: EMP-012 | C3: =IFERROR(INDEX(Empresas!$D:$D,MATCH(B3,Empresas!$A:$A,0)),"") -> FERNANDO PAVANE MASSEI ELEVADORES | D3: DOC-005 | E3: =IFERROR(INDEX(Doc_Catalogo!$B:$B,MATCH(D3,Doc_Catalogo!$A:$A,0)),"") -> CNPJ (situacao cadastral) | H3: =IF(G3="","N/A",IF(G3<TODAY(),"VENCIDO",IF(G3<=TODAY()+30,"VENCENDO","VALIDO"))) -> N/A | J3: Marcado como INDETERMINADO na planilha antiga (documento existe, sem data de vencimento fixa).
A4: REG-0003 | B4: EMP-021 | C4: =IFERROR(INDEX(Empresas!$D:$D,MATCH(B4,Empresas!$A:$A,0)),"") -> GUILHERME BITENCOURT DE FREITAS | D4: DOC-005 | E4: =IFERROR(INDEX(Doc_Catalogo!$B:$B,MATCH(D4,Doc_Catalogo!$A:$A,0)),"") -> CNPJ (situacao cadastral) | H4: =IF(G4="","N/A",IF(G4<TODAY(),"VENCIDO",IF(G4<=TODAY()+30,"VENCENDO","VALIDO"))) -> N/A | J4: Marcado como INDETERMINADO na planilha antiga (documento existe, sem data de vencimento fixa).
A5: REG-0004 | B5: EMP-016 | C5: =IFERROR(INDEX(Empresas!$D:$D,MATCH(B5,Empresas!$A:$A,0)),"") -> 34.794.316 LUIS FERNANDO BUENO DE CAMARGO | D5: DOC-005 | E5: =IFERROR(INDEX(Doc_Catalogo!$B:$B,MATCH(D5,Doc_Catalogo!$A:$A,0)),"") -> CNPJ (situacao cadastral) | H5: =IF(G5="","N/A",IF(G5<TODAY(),"VENCIDO",IF(G5<=TODAY()+30,"VENCENDO","VALIDO"))) -> N/A | J5: Marcado como INDETERMINADO na planilha antiga (documento existe, sem data de vencimento fixa).
A6: REG-0005 | B6: EMP-022 | C6: =IFERROR(INDEX(Empresas!$D:$D,MATCH(B6,Empresas!$A:$A,0)),"") -> MOSQUITO ESCADAS E ESTEIRAS ROLANTES | D6: DOC-005 | E6: =IFERROR(INDEX(Doc_Catalogo!$B:$B,MATCH(D6,Doc_Catalogo!$A:$A,0)),"") -> CNPJ (situacao cadastral) | H6: =IF(G6="","N/A",IF(G6<TODAY(),"VENCIDO",IF(G6<=TODAY()+30,"VENCENDO","VALIDO"))) -> N/A | J6: Marcado como INDETERMINADO na planilha antiga (documento existe, sem data de vencimento fixa).
A7: REG-0006 | B7: EMP-018 | C7: =IFERROR(INDEX(Empresas!$D:$D,MATCH(B7,Empresas!$A:$A,0)),"") -> OLIVER ELEVADORES LTDA | D7: DOC-005 | E7: =IFERROR(INDEX(Doc_Catalogo!$B:$B,MATCH(D7,Doc_Catalogo!$A:$A,0)),"") -> CNPJ (situacao cadastral) | H7: =IF(G7="","N/A",IF(G7<TODAY(),"VENCIDO",IF(G7<=TODAY()+30,"VENCENDO","VALIDO"))) -> N/A | J7: Marcado como INDETERMINADO na planilha antiga (documento existe, sem data de vencimento fixa).
A8: REG-0007 | B8: EMP-019 | C8: =IFERROR(INDEX(Empresas!$D:$D,MATCH(B8,Empresas!$A:$A,0)),"") -> RICARDO MANOEL INACIO | D8: DOC-005 | E8: =IFERROR(INDEX(Doc_Catalogo!$B:$B,MATCH(D8,Doc_Catalogo!$A:$A,0)),"") -> CNPJ (situacao cadastral) | H8: =IF(G8="","N/A",IF(G8<TODAY(),"VENCIDO",IF(G8<=TODAY()+30,"VENCENDO","VALIDO"))) -> N/A | J8: Marcado como INDETERMINADO na planilha antiga (documento existe, sem data de vencimento fixa).
A9: REG-0008 | B9: EMP-020 | C9: =IFERROR(INDEX(Empresas!$D:$D,MATCH(B9,Empresas!$A:$A,0)),"") -> RN SCAL SERVICOS LTDA | D9: DOC-005 | E9: =IFERROR(INDEX(Doc_Catalogo!$B:$B,MATCH(D9,Doc_Catalogo!$A:$A,0)),"") -> CNPJ (situacao cadastral) | H9: =IF(G9="","N/A",IF(G9<TODAY(),"VENCIDO",IF(G9<=TODAY()+30,"VENCENDO","VALIDO"))) -> N/A | J9: Marcado como INDETERMINADO na planilha antiga (documento existe, sem data de vencimento fixa).

Sheet Docs_Colaborador
A1: ID_Registro | B1: ID_Colaborador | C1: Nome_Colaborador | D1: ID_Documento | E1: Nome_Documento | F1: Data_Emissao | G1: Data_Vencimento | H1: Status | I1: Arquivo_Link | J1: Observacao
A2: REG-0001 | B2: COL-001 | C2: =IFERROR(INDEX(Colaboradores!$E:$E,MATCH(B2,Colaboradores!$A:$A,0)),"") -> ADEILSON FRAGOSO LEAL | D2: DOC-004 | E2: =IFERROR(INDEX(Doc_Catalogo!$B:$B,MATCH(D2,Doc_Catalogo!$A:$A,0)),"") -> ASO | G2: 46394 | H2: =IF(G2="","N/A",IF(G2<TODAY(),"VENCIDO",IF(G2<=TODAY()+30,"VENCENDO","VALIDO"))) -> VALIDO
A3: REG-0002 | B3: COL-001 | C3: =IFERROR(INDEX(Colaboradores!$E:$E,MATCH(B3,Colaboradores!$A:$A,0)),"") -> ADEILSON FRAGOSO LEAL | D3: DOC-007 | E3: =IFERROR(INDEX(Doc_Catalogo!$B:$B,MATCH(D3,Doc_Catalogo!$A:$A,0)),"") -> Certificado da NR01 — Colaborador | G3: 46370 | H3: =IF(G3="","N/A",IF(G3<TODAY(),"VENCIDO",IF(G3<=TODAY()+30,"VENCENDO","VALIDO"))) -> VALIDO
A4: REG-0003 | B4: COL-001 | C4: =IFERROR(INDEX(Colaboradores!$E:$E,MATCH(B4,Colaboradores!$A:$A,0)),"") -> ADEILSON FRAGOSO LEAL | D4: DOC-009 | E4: =IFERROR(INDEX(Doc_Catalogo!$B:$B,MATCH(D4,Doc_Catalogo!$A:$A,0)),"") -> Certificado da NR06 — Colaborador | G4: 45946 | H4: =IF(G4="","N/A",IF(G4<TODAY(),"VENCIDO",IF(G4<=TODAY()+30,"VENCENDO","VALIDO"))) -> VENCIDO
A5: REG-0004 | B5: COL-001 | C5: =IFERROR(INDEX(Colaboradores!$E:$E,MATCH(B5,Colaboradores!$A:$A,0)),"") -> ADEILSON FRAGOSO LEAL | D5: DOC-011 | E5: =IFERROR(INDEX(Doc_Catalogo!$B:$B,MATCH(D5,Doc_Catalogo!$A:$A,0)),"") -> Certificado da NR10 — Colaborador | G5: 46079 | H5: =IF(G5="","N/A",IF(G5<TODAY(),"VENCIDO",IF(G5<=TODAY()+30,"VENCENDO","VALIDO"))) -> VENCIDO
A6: REG-0005 | B6: COL-001 | C6: =IFERROR(INDEX(Colaboradores!$E:$E,MATCH(B6,Colaboradores!$A:$A,0)),"") -> ADEILSON FRAGOSO LEAL | D6: DOC-017 | E6: =IFERROR(INDEX(Doc_Catalogo!$B:$B,MATCH(D6,Doc_Catalogo!$A:$A,0)),"") -> Certificado da NR12 — Colaborador | G6: 46324 | H6: =IF(G6="","N/A",IF(G6<TODAY(),"VENCIDO",IF(G6<=TODAY()+30,"VENCENDO","VALIDO"))) -> VALIDO
A7: REG-0006 | B7: COL-001 | C7: =IFERROR(INDEX(Colaboradores!$E:$E,MATCH(B7,Colaboradores!$A:$A,0)),"") -> ADEILSON FRAGOSO LEAL | D7: DOC-023 | E7: =IFERROR(INDEX(Doc_Catalogo!$B:$B,MATCH(D7,Doc_Catalogo!$A:$A,0)),"") -> Certificado da NR18 — Colaborador | G7: 46118 | H7: =IF(G7="","N/A",IF(G7<TODAY(),"VENCIDO",IF(G7<=TODAY()+30,"VENCENDO","VALIDO"))) -> VENCIDO
A8: REG-0007 | B8: COL-001 | C8: =IFERROR(INDEX(Colaboradores!$E:$E,MATCH(B8,Colaboradores!$A:$A,0)),"") -> ADEILSON FRAGOSO LEAL | D8: DOC-031 | E8: =IFERROR(INDEX(Doc_Catalogo!$B:$B,MATCH(D8,Doc_Catalogo!$A:$A,0)),"") -> Certificado da NR35 — Colaborador | G8: 46092 | H8: =IF(G8="","N/A",IF(G8<TODAY(),"VENCIDO",IF(G8<=TODAY()+30,"VENCENDO","VALIDO"))) -> VENCIDO
A9: REG-0008 | B9: COL-004 | C9: =IFERROR(INDEX(Colaboradores!$E:$E,MATCH(B9,Colaboradores!$A:$A,0)),"") -> ANTONIO DA SILVA PALACIOS | D9: DOC-003 | E9: =IFERROR(INDEX(Doc_Catalogo!$B:$B,MATCH(D9,Doc_Catalogo!$A:$A,0)),"") -> CNH | G9: 48193 | H9: =IF(G9="","N/A",IF(G9<TODAY(),"VENCIDO",IF(G9<=TODAY()+30,"VENCENDO","VALIDO"))) -> VALIDO
A10: REG-0009 | B10: COL-004 | C10: =IFERROR(INDEX(Colaboradores!$E:$E,MATCH(B10,Colaboradores!$A:$A,0)),"") -> ANTONIO DA SILVA PALACIOS | D10: DOC-004 | E10: =IFERROR(INDEX(Doc_Catalogo!$B:$B,MATCH(D10,Doc_Catalogo!$A:$A,0)),"") -> ASO | G10: 46422 | H10: =IF(G10="","N/A",IF(G10<TODAY(),"VENCIDO",IF(G10<=TODAY()+30,"VENCENDO","VALIDO"))) -> VALIDO
A11: REG-0010 | B11: COL-004 | C11: =IFERROR(INDEX(Colaboradores!$E:$E,MATCH(B11,Colaboradores!$A:$A,0)),"") -> ANTONIO DA SILVA PALACIOS | D11: DOC-011 | E11: =IFERROR(INDEX(Doc_Catalogo!$B:$B,MATCH(D11,Doc_Catalogo!$A:$A,0)),"") -> Certificado da NR10 — Colaborador | G11: 46545 | H11: =IF(G11="","N/A",IF(G11<TODAY(),"VENCIDO",IF(G11<=TODAY()+30,"VENCENDO","VALIDO"))) -> VALIDO
A12: REG-0011 | B12: COL-004 | C12: =IFERROR(INDEX(Colaboradores!$E:$E,MATCH(B12,Colaboradores!$A:$A,0)),"") -> ANTONIO DA SILVA PALACIOS | D12: DOC-017 | E12: =IFERROR(INDEX(Doc_Catalogo!$B:$B,MATCH(D12,Doc_Catalogo!$A:$A,0)),"") -> Certificado da NR12 — Colaborador | G12: 46215 | H12: =IF(G12="","N/A",IF(G12<TODAY(),"VENCIDO",IF(G12<=TODAY()+30,"VENCENDO","VALIDO"))) -> VENCIDO
A13: REG-0012 | B13: COL-004 | C13: =IFERROR(INDEX(Colaboradores!$E:$E,MATCH(B13,Colaboradores!$A:$A,0)),"") -> ANTONIO DA SILVA PALACIOS | D13: DOC-023 | E13: =IFERROR(INDEX(Doc_Catalogo!$B:$B,MATCH(D13,Doc_Catalogo!$A:$A,0)),"") -> Certificado da NR18 — Colaborador | G13: 46788 | H13: =IF(G13="","N/A",IF(G13<TODAY(),"VENCIDO",IF(G13<=TODAY()+30,"VENCENDO","VALIDO"))) -> VALIDO
... A15: REG-0014 | B15: COL-004 | C15: =IFERROR(INDEX(Colaboradores!$E:$E,MATCH(B15,Colaboradores!$A:$A,0)),"") -> ANTONIO DA SILVA PALACIOS | D15: DOC-031 | E15: =IFERROR(INDEX(Doc_Catalogo!$B:$B,MATCH(D15,Doc_Catalogo!$A:$A,0)),"") -> Certificado da NR35 — Colaborador | G15: 46575 | H15: =IF(G15="","N/A",IF(G15<TODAY(),"VENCIDO",IF(G15<=TODAY()+30,"VENCENDO","VALIDO"))) -> VALIDO
A16: REG-0015 | B16: COL-004 | C16: =IFERROR(INDEX(Colaboradores!$E:$E,MATCH(B16,Colaboradores!$A:$A,0)),"") -> ANTONIO DA SILVA PALACIOS | D16: DOC-036 | E16: =IFERROR(INDEX(Doc_Catalogo!$B:$B,MATCH(D16,Doc_Catalogo!$A:$A,0)),"") -> Contrato de Trabalho | H16: =IF(G16="","N/A",IF(G16<TODAY(),"VENCIDO",IF(G16<=TODAY()+30,"VENCENDO","VALIDO"))) -> N/A | J16: Marcado como INDETERMINADO na planilha antiga (documento existe, sem data de vencimento fixa).
A17: REG-0016 | B17: COL-004 | C17: =IFERROR(INDEX(Colaboradores!$E:$E,MATCH(B17,Colaboradores!$A:$A,0)),"") -> ANTONIO DA SILVA PALACIOS | D17: DOC-039 | E17: =IFERROR(INDEX(Doc_Catalogo!$B:$B,MATCH(D17,Doc_Catalogo!$A:$A,0)),"") -> Ordem de Servico | H17: =IF(G17="","N/A",IF(G17<TODAY(),"VENCIDO",IF(G17<=TODAY()+30,"VENCENDO","VALIDO"))) -> N/A | J17: Marcado como INDETERMINADO na planilha antiga (documento existe, sem data de vencimento fixa).
A18: REG-0017 | B18: COL-004 | C18: =IFERROR(INDEX(Colaboradores!$E:$E,MATCH(B18,Colaboradores!$A:$A,0)),"") -> ANTONIO DA SILVA PALACIOS | D18: DOC-040 | E18: =IFERROR(INDEX(Doc_Catalogo!$B:$B,MATCH(D18,Doc_Catalogo!$A:$A,0)),"") -> Ficha de EPI Atualizada | H18: =IF(G18="","N/A",IF(G18<TODAY(),"VENCIDO",IF(G18<=TODAY()+30,"VENCENDO","VALIDO"))) -> N/A | J18: Marcado como INDETERMINADO na planilha antiga (documento existe, sem data de vencimento fixa).
A19: REG-0018 | B19: COL-005 | C19: =IFERROR(INDEX(Colaboradores!$E:$E,MATCH(B19,Colaboradores!$A:$A,0)),"") -> SERGIO MARCOS LEONCIO | D19: DOC-003 | E19: =IFERROR(INDEX(Doc_Catalogo!$B:$B,MATCH(D19,Doc_Catalogo!$A:$A,0)),"") -> CNH | G19: 46537 | H19: =IF(G19="","N/A",IF(G19<TODAY(),"VENCIDO",IF(G19<=TODAY()+30,"VENCENDO","VALIDO"))) -> VALIDO
A20: REG-0019 | B20: COL-005 | C20: =IFERROR(INDEX(Colaboradores!$E:$E,MATCH(B20,Colaboradores!$A:$A,0)),"") -> SERGIO MARCOS LEONCIO | D20: DOC-004 | E20: =IFERROR(INDEX(Doc_Catalogo!$B:$B,MATCH(D20,Doc_Catalogo!$A:$A,0)),"") -> ASO | G20: 46422 | H20: =IF(G20="","N/A",IF(G20<TODAY(),"VENCIDO",IF(G20<=TODAY()+30,"VENCENDO","VALIDO"))) -> VALIDO
A21: REG-0020 | B21: COL-005 | C21: =IFERROR(INDEX(Colaboradores!$E:$E,MATCH(B21,Colaboradores!$A:$A,0)),"") -> SERGIO MARCOS LEONCIO | D21: DOC-011 | E21: =IFERROR(INDEX(Doc_Catalogo!$B:$B,MATCH(D21,Doc_Catalogo!$A:$A,0)),"") -> Certificado da NR10 — Colaborador | G21: 46796 | H21: =IF(G21="","N/A",IF(G21<TODAY(),"VENCIDO",IF(G21<=TODAY()+30,"VENCENDO","VALIDO"))) -> VALIDO
A22: REG-0021 | B22: COL-005 | C22: =IFERROR(INDEX(Colaboradores!$E:$E,MATCH(B22,Colaboradores!$A:$A,0)),"") -> SERGIO MARCOS LEONCIO | D22: DOC-017 | E22: =IFERROR(INDEX(Doc_Catalogo!$B:$B,MATCH(D22,Doc_Catalogo!$A:$A,0)),"") -> Certificado da NR12 — Colaborador | G22: 46786 | H22: =IF(G22="","N/A",IF(G22<TODAY(),"VENCIDO",IF(G22<=TODAY()+30,"VENCENDO","VALIDO"))) -> VALIDO
A23: REG-0022 | B23: COL-005 | C23: =IFERROR(INDEX(Colaboradores!$E:$E,MATCH(B23,Colaboradores!$A:$A,0)),"") -> SERGIO MARCOS LEONCIO | D23: DOC-023 | E23: =IFERROR(INDEX(Doc_Catalogo!$B:$B,MATCH(D23,Doc_Catalogo!$A:$A,0)),"") -> Certificado da NR18 — Colaborador | G23: 46788 | H23: =IF(G23="","N/A",IF(G23<TODAY(),"VENCIDO",IF(G23<=TODAY()+30,"VENCENDO","VALIDO"))) -> VALIDO
A24: REG-0023 | B24: COL-005 | C24: =IFERROR(INDEX(Colaboradores!$E:$E,MATCH(B24,Colaboradores!$A:$A,0)),"") -> SERGIO MARCOS LEONCIO | D24: DOC-025 | E24: =IFERROR(INDEX(Doc_Catalogo!$B:$B,MATCH(D24,Doc_Catalogo!$A:$A,0)),"") -> Certificado da NR33 — Colaborador | G24: 46424 | H24: =IF(G24="","N/A",IF(G24<TODAY(),"VENCIDO",IF(G24<=TODAY()+30,"VENCENDO","VALIDO"))) -> VALIDO
A25: REG-0024 | B25: COL-005 | C25: =IFERROR(INDEX(Colaboradores!$E:$E,MATCH(B25,Colaboradores!$A:$A,0)),"") -> SERGIO MARCOS LEONCIO | D25: DOC-031 | E25: =IFERROR(INDEX(Doc_Catalogo!$B:$B,MATCH(D25,Doc_Catalogo!$A:$A,0)),"") -> Certificado da NR35 — Colaborador | G25: 46785 | H25: =IF(G25="","N/A",IF(G25<TODAY(),"VENCIDO",IF(G25<=TODAY()+30,"VENCENDO","VALIDO"))) -> VALIDO
A26: REG-0025 | B26: COL-005 | C26: =IFERROR(INDEX(Colaboradores!$E:$E,MATCH(B26,Colaboradores!$A:$A,0)),"") -> SERGIO MARCOS LEONCIO | D26: DOC-036 | E26: =IFERROR(INDEX(Doc_Catalogo!$B:$B,MATCH(D26,Doc_Catalogo!$A:$A,0)),"") -> Contrato de Trabalho | H26: =IF(G26="","N/A",IF(G26<TODAY(),"VENCIDO",IF(G26<=TODAY()+30,"VENCENDO","VALIDO"))) -> N/A | J26: Marcado como INDETERMINADO na planilha antiga (documento existe, sem data de vencimento fixa).
A27: REG-0026 | B27: COL-005 | C27: =IFERROR(INDEX(Colaboradores!$E:$E,MATCH(B27,Colaboradores!$A:$A,0)),"") -> SERGIO MARCOS LEONCIO | D27: DOC-039 | E27: =IFERROR(INDEX(Doc_Catalogo!$B:$B,MATCH(D27,Doc_Catalogo!$A:$A,0)),"") -> Ordem de Servico | H27: =IF(G27="","N/A",IF(G27<TODAY(),"VENCIDO",IF(G27<=TODAY()+30,"VENCENDO","VALIDO"))) -> N/A | J27: Marcado como INDETERMINADO na planilha antiga (documento existe, sem data de vencimento fixa).
A28: REG-0027 | B28: COL-005 | C28: =IFERROR(INDEX(Colaboradores!$E:$E,MATCH(B28,Colaboradores!$A:$A,0)),"") -> SERGIO MARCOS LEONCIO | D28: DOC-040 | E28: =IFERROR(INDEX(Doc_Catalogo!$B:$B,MATCH(D28,Doc_Catalogo!$A:$A,0)),"") -> Ficha de EPI Atualizada | H28: =IF(G28="","N/A",IF(G28<TODAY(),"VENCIDO",IF(G28<=TODAY()+30,"VENCENDO","VALIDO"))) -> N/A | J28: Marcado como INDETERMINADO na planilha antiga (documento existe, sem data de vencimento fixa).
A29: REG-0028 | B29: COL-006 | C29: =IFERROR(INDEX(Colaboradores!$E:$E,MATCH(B29,Colaboradores!$A:$A,0)),"") -> SIDNEY ALVES DOS SANTOS | D29: DOC-003 | E29: =IFERROR(INDEX(Doc_Catalogo!$B:$B,MATCH(D29,Doc_Catalogo!$A:$A,0)),"") -> CNH | G29: 49329 | H29: =IF(G29="","N/A",IF(G29<TODAY(),"VENCIDO",IF(G29<=TODAY()+30,"VENCENDO","VALIDO"))) -> VALIDO
A30: REG-0029 | B30: COL-006 | C30: =IFERROR(INDEX(Colaboradores!$E:$E,MATCH(B30,Colaboradores!$A:$A,0)),"") -> SIDNEY ALVES DOS SANTOS | D30: DOC-004 | E30: =IFERROR(INDEX(Doc_Catalogo!$B:$B,MATCH(D30,Doc_Catalogo!$A:$A,0)),"") -> ASO | G30: 46422 | H30: =IF(G30="","N/A",IF(G30<TODAY(),"VENCIDO",IF(G30<=TODAY()+30,"VENCENDO","VALIDO"))) -> VALIDO
A31: REG-0030 | B31: COL-006 | C31: =IFERROR(INDEX(Colaboradores!$E:$E,MATCH(B31,Colaboradores!$A:$A,0)),"") -> SIDNEY ALVES DOS SANTOS | D31: DOC-011 | E31: =IFERROR(INDEX(Doc_Catalogo!$B:$B,MATCH(D31,Doc_Catalogo!$A:$A,0)),"") -> Certificado da NR10 — Colaborador | G31: 46796 | H31: =IF(G31="","N/A",IF(G31<TODAY(),"VENCIDO",IF(G31<=TODAY()+30,"VENCENDO","VALIDO"))) -> VALIDO
A32: REG-0031 | B32: COL-006 | C32: =IFERROR(INDEX(Colaboradores!$E:$E,MATCH(B32,Colaboradores!$A:$A,0)),"") -> SIDNEY ALVES DOS SANTOS | D32: DOC-017 | E32: =IFERROR(INDEX(Doc_Catalogo!$B:$B,MATCH(D32,Doc_Catalogo!$A:$A,0)),"") -> Certificado da NR12 — Colaborador | G32: 46786 | H32: =IF(G32="","N/A",IF(G32<TODAY(),"VENCIDO",IF(G32<=TODAY()+30,"VENCENDO","VALIDO"))) -> VALIDO
A33: REG-0032 | B33: COL-006 | C33: =IFERROR(INDEX(Colaboradores!$E:$E,MATCH(B33,Colaboradores!$A:$A,0)),"") -> SIDNEY ALVES DOS SANTOS | D33: DOC-023 | E33: =IFERROR(INDEX(Doc_Catalogo!$B:$B,MATCH(D33,Doc_Catalogo!$A:$A,0)),"") -> Certificado da NR18 — Colaborador | G33: 46788 | H33: =IF(G33="","N/A",IF(G33<TODAY(),"VENCIDO",IF(G33<=TODAY()+30,"VENCENDO","VALIDO"))) -> VALIDO
A34: REG-0033 | B34: COL-006 | C34: =IFERROR(INDEX(Colaboradores!$E:$E,MATCH(B34,Colaboradores!$A:$A,0)),"") -> SIDNEY ALVES DOS SANTOS | D34: DOC-025 | E34: =IFERROR(INDEX(Doc_Catalogo!$B:$B,MATCH(D34,Doc_Catalogo!$A:$A,0)),"") -> Certificado da NR33 — Colaborador | G34: 46424 | H34: =IF(G34="","N/A",IF(G34<TODAY(),"VENCIDO",IF(G34<=TODAY()+30,"VENCENDO","VALIDO"))) -> VALIDO
A35: REG-0034 | B35: COL-006 | C35: =IFERROR(INDEX(Colaboradores!$E:$E,MATCH(B35,Colaboradores!$A:$A,0)),"") -> SIDNEY ALVES DOS SANTOS | D35: DOC-031 | E35: =IFERROR(INDEX(Doc_Catalogo!$B:$B,MATCH(D35,Doc_Catalogo!$A:$A,0)),"") -> Certificado da NR35 — Colaborador | G35: 46785 | H35: =IF(G35="","N/A",IF(G35<TODAY(),"VENCIDO",IF(G35<=TODAY()+30,"VENCENDO","VALIDO"))) -> VALIDO
A36: REG-0035 | B36: COL-006 | C36: =IFERROR(INDEX(Colaboradores!$E:$E,MATCH(B36,Colaboradores!$A:$A,0)),"") -> SIDNEY ALVES DOS SANTOS | D36: DOC-036 | E36: =IFERROR(INDEX(Doc_Catalogo!$B:$B,MATCH(D36,Doc_Catalogo!$A:$A,0)),"") -> Contrato de Trabalho | H36: =IF(G36="","N/A",IF(G36<TODAY(),"VENCIDO",IF(G36<=TODAY()+30,"VENCENDO","VALIDO"))) -> N/A | J36: Marcado como INDETERMINADO na planilha antiga (documento existe, sem data de vencimento fixa).
A37: REG-0036 | B37: COL-006 | C37: =IFERROR(INDEX(Colaboradores!$E:$E,MATCH(B37,Colaboradores!$A:$A,0)),"") -> SIDNEY ALVES DOS SANTOS | D37: DOC-039 | E37: =IFERROR(INDEX(Doc_Catalogo!$B:$B,MATCH(D37,Doc_Catalogo!$A:$A,0)),"") -> Ordem de Servico | H37: =IF(G37="","N/A",IF(G37<TODAY(),"VENCIDO",IF(G37<=TODAY()+30,"VENCENDO","VALIDO"))) -> N/A | J37: Marcado como INDETERMINADO na planilha antiga (documento existe, sem data de vencimento fixa).
A38: REG-0037 | B38: COL-006 | C38: =IFERROR(INDEX(Colaboradores!$E:$E,MATCH(B38,Colaboradores!$A:$A,0)),"") -> SIDNEY ALVES DOS SANTOS | D38: DOC-040 | E38: =IFERROR(INDEX(Doc_Catalogo!$B:$B,MATCH(D38,Doc_Catalogo!$A:$A,0)),"") -> Ficha de EPI Atualizada | H38: =IF(G38="","N/A",IF(G38<TODAY(),"VENCIDO",IF(G38<=TODAY()+30,"VENCENDO","VALIDO"))) -> N/A | J38: Marcado como INDETERMINADO na planilha antiga (documento existe, sem data de vencimento fixa).
A39: REG-0038 | B39: COL-008 | C39: =IFERROR(INDEX(Colaboradores!$E:$E,MATCH(B39,Colaboradores!$A:$A,0)),"") -> DANIEL SCHURT | D39: DOC-004 | E39: =IFERROR(INDEX(Doc_Catalogo!$B:$B,MATCH(D39,Doc_Catalogo!$A:$A,0)),"") -> ASO | G39: 46550 | H39: =IF(G39="","N/A",IF(G39<TODAY(),"VENCIDO",IF(G39<=TODAY()+30,"VENCENDO","VALIDO"))) -> VALIDO
A40: REG-0039 | B40: COL-008 | C40: =IFERROR(INDEX(Colaboradores!$E:$E,MATCH(B40,Colaboradores!$A:$A,0)),"") -> DANIEL SCHURT | D40: DOC-009 | E40: =IFERROR(INDEX(Doc_Catalogo!$B:$B,MATCH(D40,Doc_Catalogo!$A:$A,0)),"") -> Certificado da NR06 — Colaborador | G40: 46539 | H40: =IF(G40="","N/A",IF(G40<TODAY(),"VENCIDO",IF(G40<=TODAY()+30,"VENCENDO","VALIDO"))) -> VALIDO
A41: REG-0040 | B41: COL-008 | C41: =IFERROR(INDEX(Colaboradores!$E:$E,MATCH(B41,Colaboradores!$A:$A,0)),"") -> DANIEL SCHURT | D41: DOC-011 | E41: =IFERROR(INDEX(Doc_Catalogo!$B:$B,MATCH(D41,Doc_Catalogo!$A:$A,0)),"") -> Certificado da NR10 — Colaborador | G41: 46786 | H41: =IF(G41="","N/A",IF(G41<TODAY(),"VENCIDO",IF(G41<=TODAY()+30,"VENCENDO","VALIDO"))) -> VALIDO
A42: REG-0041 | B42: COL-008 | C42: =IFERROR(INDEX(Colaboradores!$E:$E,MATCH(B42,Colaboradores!$A:$A,0)),"") -> DANIEL SCHURT | D42: DOC-015 | E42: =IFERROR(INDEX(Doc_Catalogo!$B:$B,MATCH(D42,Doc_Catalogo!$A:$A,0)),"") -> Certificado da NR11 — Colaborador | G42: 46542 | H42: =IF(G42="","N/A",IF(G42<TODAY(),"VENCIDO",IF(G42<=TODAY()+30,"VENCENDO","VALIDO"))) -> VALIDO
A43: REG-0042 | B43: COL-008 | C43: =IFERROR(INDEX(Colaboradores!$E:$E,MATCH(B43,Colaboradores!$A:$A,0)),"") -> DANIEL SCHURT | D43: DOC-023 | E43: =IFERROR(INDEX(Doc_Catalogo!$B:$B,MATCH(D43,Doc_Catalogo!$A:$A,0)),"") -> Certificado da NR18 — Colaborador | G43: 46787 | H43: =IF(G43="","N/A",IF(G43<TODAY(),"VENCIDO",IF(G43<=TODAY()+30,"VENCENDO","VALIDO"))) -> VALIDO
A44: REG-0043 | B44: COL-008 | C44: =IFERROR(INDEX(Colaboradores!$E:$E,MATCH(B44,Colaboradores!$A:$A,0)),"") -> DANIEL SCHURT | D44: DOC-025 | E44: =IFERROR(INDEX(Doc_Catalogo!$B:$B,MATCH(D44,Doc_Catalogo!$A:$A,0)),"") -> Certificado da NR33 — Colaborador | G44: 46541 | H44: =IF(G44="","N/A",IF(G44<TODAY(),"VENCIDO",IF(G44<=TODAY()+30,"VENCENDO","VALIDO"))) -> VALIDO
A45: REG-0044 | B45: COL-008 | C45: =IFERROR(INDEX(Colaboradores!$E:$E,MATCH(B45,Colaboradores!$A:$A,0)),"") -> DANIEL SCHURT | D45: DOC-031 | E45: =IFERROR(INDEX(Doc_Catalogo!$B:$B,MATCH(D45,Doc_Catalogo!$A:$A,0)),"") -> Certificado da NR35 — Colaborador | G45: 46788 | H45: =IF(G45="","N/A",IF(G45<TODAY(),"VENCIDO",IF(G45<=TODAY()+30,"VENCENDO","VALIDO"))) -> VALIDO | J45: Corrigido de '05/022028' (provavel 05/02/2028, faltava a barra) — confirmar.
A46: REG-0045 | B46: COL-008 | C46: =IFERROR(INDEX(Colaboradores!$E:$E,MATCH(B46,Colaboradores!$A:$A,0)),"") -> DANIEL SCHURT | D46: DOC-040 | E46: =IFERROR(INDEX(Doc_Catalogo!$B:$B,MATCH(D46,Doc_Catalogo!$A:$A,0)),"") -> Ficha de EPI Atualizada | H46: =IF(G46="","N/A",IF(G46<TODAY(),"VENCIDO",IF(G46<=TODAY()+30,"VENCENDO","VALIDO"))) -> N/A | J46: Marcado como INDETERMINADO na planilha antiga (documento existe, sem data de vencimento fixa).
A47: REG-0046 | B47: COL-034 | C47: =IFERROR(INDEX(Colaboradores!$E:$E,MATCH(B47,Colaboradores!$A:$A,0)),"") -> ELSON RICARDO BATISTA PINTO | D47: DOC-009 | E47: =IFERROR(INDEX(Doc_Catalogo!$B:$B,MATCH(D47,Doc_Catalogo!$A:$A,0)),"") -> Certificado da NR06 — Colaborador | G47: 46455 | H47: =IF(G47="","N/A",IF(G47<TODAY(),"VENCIDO",IF(G47<=TODAY()+30,"VENCENDO","VALIDO"))) -> VALIDO
A48: REG-0047 | B48: COL-034 | C48: =IFERROR(INDEX(Colaboradores!$E:$E,MATCH(B48,Colaboradores!$A:$A,0)),"") -> ELSON RICARDO BATISTA PINTO | D48: DOC-011 | E48: =IFERROR(INDEX(Doc_Catalogo!$B:$B,MATCH(D48,Doc_Catalogo!$A:$A,0)),"") -> Certificado da NR10 — Colaborador | G48: 46452 | H48: =IF(G48="","N/A",IF(G48<TODAY(),"VENCIDO",IF(G48<=TODAY()+30,"VENCENDO","VALIDO"))) -> VALIDO
A49: REG-0048 | B49: COL-034 | C49: =IFERROR(INDEX(Colaboradores!$E:$E,MATCH(B49,Colaboradores!$A:$A,0)),"") -> ELSON RICARDO BATISTA PINTO | D49: DOC-017 | E49: =IFERROR(INDEX(Doc_Catalogo!$B:$B,MATCH(D49,Doc_Catalogo!$A:$A,0)),"") -> Certificado da NR12 — Colaborador | G49: 46436 | H49: =IF(G49="","N/A",IF(G49<TODAY(),"VENCIDO",IF(G49<=TODAY()+30,"VENCENDO","VALIDO"))) -> VALIDO
A50: REG-0049 | B50: COL-034 | C50: =IFERROR(INDEX(Colaboradores!$E:$E,MATCH(B50,Colaboradores!$A:$A,0)),"") -> ELSON RICARDO BATISTA PINTO | D50: DOC-023 | E50: =IFERROR(INDEX(Doc_Catalogo!$B:$B,MATCH(D50,Doc_Catalogo!$A:$A,0)),"") -> Certificado da NR18 — Colaborador | G50: 46447 | H50: =IF(G50="","N/A",IF(G50<TODAY(),"VENCIDO",IF(G50<=TODAY()+30,"VENCENDO","VALIDO"))) -> VALIDO
A51: REG-0050 | B51: COL-034 | C51: =IFERROR(INDEX(Colaboradores!$E:$E,MATCH(B51,Colaboradores!$A:$A,0)),"") -> ELSON RICARDO BATISTA PINTO | D51: DOC-025 | E51: =IFERROR(INDEX(Doc_Catalogo!$B:$B,MATCH(D51,Doc_Catalogo!$A:$A,0)),"") -> Certificado da NR33 — Colaborador | G51: 46469 | H51: =IF(G51="","N/A",IF(G51<TODAY(),"VENCIDO",IF(G51<=TODAY()+30,"VENCENDO","VALIDO"))) -> VALIDO
A52: REG-0051 | B52: COL-034 | C52: =IFERROR(INDEX(Colaboradores!$E:$E,MATCH(B52,Colaboradores!$A:$A,0)),"") -> ELSON RICARDO BATISTA PINTO | D52: DOC-027 | E52: =IFERROR(INDEX(Doc_Catalogo!$B:$B,MATCH(D52,Doc_Catalogo!$A:$A,0)),"") -> Carta de anuencia (NR33) — Colaborador | G52: 46469 | H52: =IF(G52="","N/A",IF(G52<TODAY(),"VENCIDO",IF(G52<=TODAY()+30,"VENCENDO","VALIDO"))) -> VALIDO
A53: REG-0052 | B53: COL-034 | C53: =IFERROR(INDEX(Colaboradores!$E:$E,MATCH(B53,Colaboradores!$A:$A,0)),"") -> ELSON RICARDO BATISTA PINTO | D53: DOC-031 | E53: =IFERROR(INDEX(Doc_Catalogo!$B:$B,MATCH(D53,Doc_Catalogo!$A:$A,0)),"") -> Certificado da NR35 — Colaborador | G53: 46466 | H53: =IF(G53="","N/A",IF(G53<TODAY(),"VENCIDO",IF(G53<=TODAY()+30,"VENCENDO","VALIDO"))) -> VALIDO
A54: REG-0053 | B54: COL-034 | C54: =IFERROR(INDEX(Colaboradores!$E:$E,MATCH(B54,Colaboradores!$A:$A,0)),"") -> ELSON RICARDO BATISTA PINTO | D54: DOC-033 | E54: =IFERROR(INDEX(Doc_Catalogo!$B:$B,MATCH(D54,Doc_Catalogo!$A:$A,0)),"") -> Carta de anuencia (NR35) — Colaborador | G54: 46466 | H54: =IF(G54="","N/A",IF(G54<TODAY(),"VENCIDO",IF(G54<=TODAY()+30,"VENCENDO","VALIDO"))) -> VALIDO
A55: REG-0054 | B55: COL-034 | C55: =IFERROR(INDEX(Colaboradores!$E:$E,MATCH(B55,Colaboradores!$A:$A,0)),"") -> ELSON RICARDO BATISTA PINTO | D55: DOC-037 | E55: =IFERROR(INDEX(Doc_Catalogo!$B:$B,MATCH(D55,Doc_Catalogo!$A:$A,0)),"") -> Contrato Experiencia | H55: =IF(G55="","N/A",IF(G55<TODAY(),"VENCIDO",IF(G55<=TODAY()+30,"VENCENDO","VALIDO"))) -> N/A | J55: Marcado como INDETERMINADO na planilha antiga (documento existe, sem data de vencimento fixa).
A56: REG-0055 | B56: COL-033 | C56: =IFERROR(INDEX(Colaboradores!$E:$E,MATCH(B56,Colaboradores!$A:$A,0)),"") -> DANIEL APARECIDO DOS REIS FELICIANO | D56: DOC-004 | E56: =IFERROR(INDEX(Doc_Catalogo!$B:$B,MATCH(D56,Doc_Catalogo!$A:$A,0)),"") -> ASO | G56: 46395 | H56: =IF(G56="","N/A",IF(G56<TODAY(),"VENCIDO",IF(G56<=TODAY()+30,"VENCENDO","VALIDO"))) -> VALIDO
A57: REG-0056 | B57: COL-033 | C57: =IFERROR(INDEX(Colaboradores!$E:$E,MATCH(B57,Colaboradores!$A:$A,0)),"") -> DANIEL APARECIDO DOS REIS FELICIANO | D57: DOC-011 | E57: =IFERROR(INDEX(Doc_Catalogo!$B:$B,MATCH(D57,Doc_Catalogo!$A:$A,0)),"") -> Certificado da NR10 — Colaborador | G57: 46911 | H57: =IF(G57="","N/A",IF(G57<TODAY(),"VENCIDO",IF(G57<=TODAY()+30,"VENCENDO","VALIDO"))) -> VALIDO
A58: REG-0057 | B58: COL-033 | C58: =IFERROR(INDEX(Colaboradores!$E:$E,MATCH(B58,Colaboradores!$A:$A,0)),"") -> DANIEL APARECIDO DOS REIS FELICIANO | D58: DOC-017 | E58: =IFERROR(INDEX(Doc_Catalogo!$B:$B,MATCH(D58,Doc_Catalogo!$A:$A,0)),"") -> Certificado da NR12 — Colaborador | G58: 46928 | H58: =IF(G58="","N/A",IF(G58<TODAY(),"VENCIDO",IF(G58<=TODAY()+30,"VENCENDO","VALIDO"))) -> VALIDO
A59: REG-0058 | B59: COL-033 | C59: =IFERROR(INDEX(Colaboradores!$E:$E,MATCH(B59,Colaboradores!$A:$A,0)),"") -> DANIEL APARECIDO DOS REIS FELICIANO | D59: DOC-023 | E59: =IFERROR(INDEX(Doc_Catalogo!$B:$B,MATCH(D59,Doc_Catalogo!$A:$A,0)),"") -> Certificado da NR18 — Colaborador | G59: 46397 | H59: =IF(G59="","N/A",IF(G59<TODAY(),"VENCIDO",IF(G59<=TODAY()+30,"VENCENDO","VALIDO"))) -> VALIDO
A60: REG-0059 | B60: COL-033 | C60: =IFERROR(INDEX(Colaboradores!$E:$E,MATCH(B60,Colaboradores!$A:$A,0)),"") -> DANIEL APARECIDO DOS REIS FELICIANO | D60: DOC-031 | E60: =IFERROR(INDEX(Doc_Catalogo!$B:$B,MATCH(D60,Doc_Catalogo!$A:$A,0)),"") -> Certificado da NR35 — Colaborador | G60: 46184 | H60: =IF(G60="","N/A",IF(G60<TODAY(),"VENCIDO",IF(G60<=TODAY()+30,"VENCENDO","VALIDO"))) -> VENCIDO
A61: REG-0060 | B61: COL-033 | C61: =IFERROR(INDEX(Colaboradores!$E:$E,MATCH(B61,Colaboradores!$A:$A,0)),"") -> DANIEL APARECIDO DOS REIS FELICIANO | D61: DOC-034 | E61: =IFERROR(INDEX(Doc_Catalogo!$B:$B,MATCH(D61,Doc_Catalogo!$A:$A,0)),"") -> Ficha de Registro | H61: =IF(G61="","N/A",IF(G61<TODAY(),"VENCIDO",IF(G61<=TODAY()+30,"VENCENDO","VALIDO"))) -> N/A | J61: Marcado como INDETERMINADO na planilha antiga (documento existe, sem data de vencimento fixa).
A62: REG-0061 | B62: COL-033 | C62: =IFERROR(INDEX(Colaboradores!$E:$E,MATCH(B62,Colaboradores!$A:$A,0)),"") -> DANIEL APARECIDO DOS REIS FELICIANO | D62: DOC-035 | E62: =IFERROR(INDEX(Doc_Catalogo!$B:$B,MATCH(D62,Doc_Catalogo!$A:$A,0)),"") -> E-social | H62: =IF(G62="","N/A",IF(G62<TODAY(),"VENCIDO",IF(G62<=TODAY()+30,"VENCENDO","VALIDO"))) -> N/A | J62: Marcado como INDETERMINADO na planilha antiga (documento existe, sem data de vencimento fixa).
A63: REG-0062 | B63: COL-033 | C63: =IFERROR(INDEX(Colaboradores!$E:$E,MATCH(B63,Colaboradores!$A:$A,0)),"") -> DANIEL APARECIDO DOS REIS FELICIANO | D63: DOC-037 | E63: =IFERROR(INDEX(Doc_Catalogo!$B:$B,MATCH(D63,Doc_Catalogo!$A:$A,0)),"") -> Contrato Experiencia | H63: =IF(G63="","N/A",IF(G63<TODAY(),"VENCIDO",IF(G63<=TODAY()+30,"VENCENDO","VALIDO"))) -> N/A | J63: Marcado como INDETERMINADO na planilha antiga (documento existe, sem data de vencimento fixa).
A64: REG-0063 | B64: COL-033 | C64: =IFERROR(INDEX(Colaboradores!$E:$E,MATCH(B64,Colaboradores!$A:$A,0)),"") -> DANIEL APARECIDO DOS REIS FELICIANO | D64: DOC-040 | E64: =IFERROR(INDEX(Doc_Catalogo!$B:$B,MATCH(D64,Doc_Catalogo!$A:$A,0)),"") -> Ficha de EPI Atualizada | H64: =IF(G64="","N/A",IF(G64<TODAY(),"VENCIDO",IF(G64<=TODAY()+30,"VENCENDO","VALIDO"))) -> N/A | J64: Marcado como INDETERMINADO na planilha antiga (documento existe, sem data de vencimento fixa).
A65: REG-0064 | B65: COL-038 | C65: =IFERROR(INDEX(Colaboradores!$E:$E,MATCH(B65,Colaboradores!$A:$A,0)),"") -> MATHEUS MOTA RIBEIRO | D65: DOC-003 | E65: =IFERROR(INDEX(Doc_Catalogo!$B:$B,MATCH(D65,Doc_Catalogo!$A:$A,0)),"") -> CNH | G65: 48744 | H65: =IF(G65="","N/A",IF(G65<TODAY(),"VENCIDO",IF(G65<=TODAY()+30,"VENCENDO","VALIDO"))) -> VALIDO
A66: REG-0065 | B66: COL-038 | C66: =IFERROR(INDEX(Colaboradores!$E:$E,MATCH(B66,Colaboradores!$A:$A,0)),"") -> MATHEUS MOTA RIBEIRO | D66: DOC-004 | E66: =IFERROR(INDEX(Doc_Catalogo!$B:$B,MATCH(D66,Doc_Catalogo!$A:$A,0)),"") -> ASO | G66: 46322 | H66: =IF(G66="","N/A",IF(G66<TODAY(),"VENCIDO",IF(G66<=TODAY()+30,"VENCENDO","VALIDO"))) -> VALIDO
A67: REG-0066 | B67: COL-038 | C67: =IFERROR(INDEX(Colaboradores!$E:$E,MATCH(B67,Colaboradores!$A:$A,0)),"") -> MATHEUS MOTA RIBEIRO | D67: DOC-011 | E67: =IFERROR(INDEX(Doc_Catalogo!$B:$B,MATCH(D67,Doc_Catalogo!$A:$A,0)),"") -> Certificado da NR10 — Colaborador | G67: 46689 | H67: =IF(G67="","N/A",IF(G67<TODAY(),"VENCIDO",IF(G67<=TODAY()+30,"VENCENDO","VALIDO"))) -> VALIDO
A68: REG-0067 | B68: COL-038 | C68: =IFERROR(INDEX(Colaboradores!$E:$E,MATCH(B68,Colaboradores!$A:$A,0)),"") -> MATHEUS MOTA RIBEIRO | D68: DOC-017 | E68: =IFERROR(INDEX(Doc_Catalogo!$B:$B,MATCH(D68,Doc_Catalogo!$A:$A,0)),"") -> Certificado da NR12 — Colaborador | G68: 46690 | H68: =IF(G68="","N/A",IF(G68<TODAY(),"VENCIDO",IF(G68<=TODAY()+30,"VENCENDO","VALIDO"))) -> VALIDO
A69: REG-0068 | B69: COL-038 | C69: =IFERROR(INDEX(Colaboradores!$E:$E,MATCH(B69,Colaboradores!$A:$A,0)),"") -> MATHEUS MOTA RIBEIRO | D69: DOC-023 | E69: =IFERROR(INDEX(Doc_Catalogo!$B:$B,MATCH(D69,Doc_Catalogo!$A:$A,0)),"") -> Certificado da NR18 — Colaborador | G69: 46691 | H69: =IF(G69="","N/A",IF(G69<TODAY(),"VENCIDO",IF(G69<=TODAY()+30,"VENCENDO","VALIDO"))) -> VALIDO
A70: REG-0069 | B70: COL-038 | C70: =IFERROR(INDEX(Colaboradores!$E:$E,MATCH(B70,Colaboradores!$A:$A,0)),"") -> MATHEUS MOTA RIBEIRO | D70: DOC-025 | E70: =IFERROR(INDEX(Doc_Catalogo!$B:$B,MATCH(D70,Doc_Catalogo!$A:$A,0)),"") -> Certificado da NR33 — Colaborador | G70: 46329 | H70: =IF(G70="","N/A",IF(G70<TODAY(),"VENCIDO",IF(G70<=TODAY()+30,"VENCENDO","VALIDO"))) -> VALIDO
A71: REG-0070 | B71: COL-038 | C71: =IFERROR(INDEX(Colaboradores!$E:$E,MATCH(B71,Colaboradores!$A:$A,0)),"") -> MATHEUS MOTA RIBEIRO | D71: DOC-031 | E71: =IFERROR(INDEX(Doc_Catalogo!$B:$B,MATCH(D71,Doc_Catalogo!$A:$A,0)),"") -> Certificado da NR35 — Colaborador | G71: 46664 | H71: =IF(G71="","N/A",IF(G71<TODAY(),"VENCIDO",IF(G71<=TODAY()+30,"VENCENDO","VALIDO"))) -> VALIDO
A72: REG-0071 | B72: COL-038 | C72: =IFERROR(INDEX(Colaboradores!$E:$E,MATCH(B72,Colaboradores!$A:$A,0)),"") -> MATHEUS MOTA RIBEIRO | D72: DOC-034 | E72: =IFERROR(INDEX(Doc_Catalogo!$B:$B,MATCH(D72,Doc_Catalogo!$A:$A,0)),"") -> Ficha de Registro | H72: =IF(G72="","N/A",IF(G72<TODAY(),"VENCIDO",IF(G72<=TODAY()+30,"VENCENDO","VALIDO"))) -> N/A | J72: Marcado como INDETERMINADO na planilha antiga (documento existe, sem data de vencimento fixa).
A73: REG-0072 | B73: COL-038 | C73: =IFERROR(INDEX(Colaboradores!$E:$E,MATCH(B73,Colaboradores!$A:$A,0)),"") -> MATHEUS MOTA RIBEIRO | D73: DOC-035 | E73: =IFERROR(INDEX(Doc_Catalogo!$B:$B,MATCH(D73,Doc_Catalogo!$A:$A,0)),"") -> E-social | H73: =IF(G73="","N/A",IF(G73<TODAY(),"VENCIDO",IF(G73<=TODAY()+30,"VENCENDO","VALIDO"))) -> N/A | J73: Marcado como INDETERMINADO na planilha antiga (documento existe, sem data de vencimento fixa).
A74: REG-0073 | B74: COL-038 | C74: =IFERROR(INDEX(Colaboradores!$E:$E,MATCH(B74,Colaboradores!$A:$A,0)),"") -> MATHEUS MOTA RIBEIRO | D74: DOC-037 | E74: =IFERROR(INDEX(Doc_Catalogo!$B:$B,MATCH(D74,Doc_Catalogo!$A:$A,0)),"") -> Contrato Experiencia | H74: =IF(G74="","N/A",IF(G74<TODAY(),"VENCIDO",IF(G74<=TODAY()+30,"VENCENDO","VALIDO"))) -> N/A | J74: Marcado como INDETERMINADO na planilha antiga (documento existe, sem data de vencimento fixa).
A75: REG-0074 | B75: COL-038 | C75: =IFERROR(INDEX(Colaboradores!$E:$E,MATCH(B75,Colaboradores!$A:$A,0)),"") -> MATHEUS MOTA RIBEIRO | D75: DOC-040 | E75: =IFERROR(INDEX(Doc_Catalogo!$B:$B,MATCH(D75,Doc_Catalogo!$A:$A,0)),"") -> Ficha de EPI Atualizada | H75: =IF(G75="","N/A",IF(G75<TODAY(),"VENCIDO",IF(G75<=TODAY()+30,"VENCENDO","VALIDO"))) -> N/A | J75: Marcado como INDETERMINADO na planilha antiga (documento existe, sem data de vencimento fixa).
A76: REG-0075 | B76: COL-040 | C76: =IFERROR(INDEX(Colaboradores!$E:$E,MATCH(B76,Colaboradores!$A:$A,0)),"") -> YOANDERSON COSTA DOS SANTOS | D76: DOC-003 | E76: =IFERROR(INDEX(Doc_Catalogo!$B:$B,MATCH(D76,Doc_Catalogo!$A:$A,0)),"") -> CNH | G76: 48046 | H76: =IF(G76="","N/A",IF(G76<TODAY(),"VENCIDO",IF(G76<=TODAY()+30,"VENCENDO","VALIDO"))) -> VALIDO
A77: REG-0076 | B77: COL-040 | C77: =IFERROR(INDEX(Colaboradores!$E:$E,MATCH(B77,Colaboradores!$A:$A,0)),"") -> YOANDERSON COSTA DOS SANTOS | D77: DOC-004 | E77: =IFERROR(INDEX(Doc_Catalogo!$B:$B,MATCH(D77,Doc_Catalogo!$A:$A,0)),"") -> ASO | G77: 46511 | H77: =IF(G77="","N/A",IF(G77<TODAY(),"VENCIDO",IF(G77<=TODAY()+30,"VENCENDO","VALIDO"))) -> VALIDO
A78: REG-0077 | B78: COL-040 | C78: =IFERROR(INDEX(Colaboradores!$E:$E,MATCH(B78,Colaboradores!$A:$A,0)),"") -> YOANDERSON COSTA DOS SANTOS | D78: DOC-009 | E78: =IFERROR(INDEX(Doc_Catalogo!$B:$B,MATCH(D78,Doc_Catalogo!$A:$A,0)),"") -> Certificado da NR06 — Colaborador | G78: 46565 | H78: =IF(G78="","N/A",IF(G78<TODAY(),"VENCIDO",IF(G78<=TODAY()+30,"VENCENDO","VALIDO"))) -> VALIDO
A79: REG-0078 | B79: COL-040 | C79: =IFERROR(INDEX(Colaboradores!$E:$E,MATCH(B79,Colaboradores!$A:$A,0)),"") -> YOANDERSON COSTA DOS SANTOS | D79: DOC-011 | E79: =IFERROR(INDEX(Doc_Catalogo!$B:$B,MATCH(D79,Doc_Catalogo!$A:$A,0)),"") -> Certificado da NR10 — Colaborador | G79: 46180 | H79: =IF(G79="","N/A",IF(G79<TODAY(),"VENCIDO",IF(G79<=TODAY()+30,"VENCENDO","VALIDO"))) -> VENCIDO
A80: REG-0079 | B80: COL-040 | C80: =IFERROR(INDEX(Colaboradores!$E:$E,MATCH(B80,Colaboradores!$A:$A,0)),"") -> YOANDERSON COSTA DOS SANTOS | D80: DOC-017 | E80: =IFERROR(INDEX(Doc_Catalogo!$B:$B,MATCH(D80,Doc_Catalogo!$A:$A,0)),"") -> Certificado da NR12 — Colaborador | G80: 46197 | H80: =IF(G80="","N/A",IF(G80<TODAY(),"VENCIDO",IF(G80<=TODAY()+30,"VENCENDO","VALIDO"))) -> VENCIDO
A81: REG-0080 | B81: COL-040 | C81: =IFERROR(INDEX(Colaboradores!$E:$E,MATCH(B81,Colaboradores!$A:$A,0)),"") -> YOANDERSON COSTA DOS SANTOS | D81: DOC-023 | E81: =IFERROR(INDEX(Doc_Catalogo!$B:$B,MATCH(D81,Doc_Catalogo!$A:$A,0)),"") -> Certificado da NR18 — Colaborador | G81: 46558 | H81: =IF(G81="","N/A",IF(G81<TODAY(),"VENCIDO",IF(G81<=TODAY()+30,"VENCENDO","VALIDO"))) -> VALIDO
A82: REG-0081 | B82: COL-040 | C82: =IFERROR(INDEX(Colaboradores!$E:$E,MATCH(B82,Colaboradores!$A:$A,0)),"") -> YOANDERSON COSTA DOS SANTOS | D82: DOC-025 | E82: =IFERROR(INDEX(Doc_Catalogo!$B:$B,MATCH(D82,Doc_Catalogo!$A:$A,0)),"") -> Certificado da NR33 — Colaborador | G82: 45825 | H82: =IF(G82="","N/A",IF(G82<TODAY(),"VENCIDO",IF(G82<=TODAY()+30,"VENCENDO","VALIDO"))) -> VENCIDO
A83: REG-0082 | B83: COL-040 | C83: =IFERROR(INDEX(Colaboradores!$E:$E,MATCH(B83,Colaboradores!$A:$A,0)),"") -> YOANDERSON COSTA DOS SANTOS | D83: DOC-031 | E83: =IFERROR(INDEX(Doc_Catalogo!$B:$B,MATCH(D83,Doc_Catalogo!$A:$A,0)),"") -> Certificado da NR35 — Colaborador | G83: 46184 | H83: =IF(G83="","N/A",IF(G83<TODAY(),"VENCIDO",IF(G83<=TODAY()+30,"VENCENDO","VALIDO"))) -> VENCIDO
A84: REG-0083 | B84: COL-040 | C84: =IFERROR(INDEX(Colaboradores!$E:$E,MATCH(B84,Colaboradores!$A:$A,0)),"") -> YOANDERSON COSTA DOS SANTOS | D84: DOC-035 | E84: =IFERROR(INDEX(Doc_Catalogo!$B:$B,MATCH(D84,Doc_Catalogo!$A:$A,0)),"") -> E-social | H84: =IF(G84="","N/A",IF(G84<TODAY(),"VENCIDO",IF(G84<=TODAY()+30,"VENCENDO","VALIDO"))) -> N/A | J84: Marcado como INDETERMINADO na planilha antiga (documento existe, sem data de vencimento fixa).
A85: REG-0084 | B85: COL-040 | C85: =IFERROR(INDEX(Colaboradores!$E:$E,MATCH(B85,Colaboradores!$A:$A,0)),"") -> YOANDERSON COSTA DOS SANTOS | D85: DOC-037 | E85: =IFERROR(INDEX(Doc_Catalogo!$B:$B,MATCH(D85,Doc_Catalogo!$A:$A,0)),"") -> Contrato Experiencia | H85: =IF(G85="","N/A",IF(G85<TODAY(),"VENCIDO",IF(G85<=TODAY()+30,"VENCENDO","VALIDO"))) -> N/A | J85: Marcado como INDETERMINADO na planilha antiga (documento existe, sem data de vencimento fixa).
A86: REG-0085 | B86: COL-031 | C86: =IFERROR(INDEX(Colaboradores!$E:$E,MATCH(B86,Colaboradores!$A:$A,0)),"") -> BELION FELIPE FERNANDES CORREIA | D86: DOC-004 | E86: =IFERROR(INDEX(Doc_Catalogo!$B:$B,MATCH(D86,Doc_Catalogo!$A:$A,0)),"") -> ASO | G86: 45910 | H86: =IF(G86="","N/A",IF(G86<TODAY(),"VENCIDO",IF(G86<=TODAY()+30,"VENCENDO","VALIDO"))) -> VENCIDO
A87: REG-0086 | B87: COL-031 | C87: =IFERROR(INDEX(Colaboradores!$E:$E,MATCH(B87,Colaboradores!$A:$A,0)),"") -> BELION FELIPE FERNANDES CORREIA | D87: DOC-034 | E87: =IFERROR(INDEX(Doc_Catalogo!$B:$B,MATCH(D87,Doc_Catalogo!$A:$A,0)),"") -> Ficha de Registro | H87: =IF(G87="","N/A",IF(G87<TODAY(),"VENCIDO",IF(G87<=TODAY()+30,"VENCENDO","VALIDO"))) -> N/A | J87: Marcado como INDETERMINADO na planilha antiga (documento existe, sem data de vencimento fixa).
A88: REG-0087 | B88: COL-031 | C88: =IFERROR(INDEX(Colaboradores!$E:$E,MATCH(B88,Colaboradores!$A:$A,0)),"") -> BELION FELIPE FERNANDES CORREIA | D88: DOC-035 | E88: =IFERROR(INDEX(Doc_Catalogo!$B:$B,MATCH(D88,Doc_Catalogo!$A:$A,0)),"") -> E-social | H88: =IF(G88="","N/A",IF(G88<TODAY(),"VENCIDO",IF(G88<=TODAY()+30,"VENCENDO","VALIDO"))) -> N/A | J88: Marcado como INDETERMINADO na planilha antiga (documento existe, sem data de vencimento fixa).
A89: REG-0088 | B89: COL-031 | C89: =IFERROR(INDEX(Colaboradores!$E:$E,MATCH(B89,Colaboradores!$A:$A,0)),"") -> BELION FELIPE FERNANDES CORREIA | D89: DOC-037 | E89: =IFERROR(INDEX(Doc_Catalogo!$B:$B,MATCH(D89,Doc_Catalogo!$A:$A,0)),"") -> Contrato Experiencia | H89: =IF(G89="","N/A",IF(G89<TODAY(),"VENCIDO",IF(G89<=TODAY()+30,"VENCENDO","VALIDO"))) -> N/A | J89: Marcado como INDETERMINADO na planilha antiga (documento existe, sem data de vencimento fixa).
A90: REG-0089 | B90: COL-031 | C90: =IFERROR(INDEX(Colaboradores!$E:$E,MATCH(B90,Colaboradores!$A:$A,0)),"") -> BELION FELIPE FERNANDES CORREIA | D90: DOC-039 | E90: =IFERROR(INDEX(Doc_Catalogo!$B:$B,MATCH(D90,Doc_Catalogo!$A:$A,0)),"") -> Ordem de Servico | H90: =IF(G90="","N/A",IF(G90<TODAY(),"VENCIDO",IF(G90<=TODAY()+30,"VENCENDO","VALIDO"))) -> N/A | J90: Marcado como INDETERMINADO na planilha antiga (documento existe, sem data de vencimento fixa).
A91: REG-0090 | B91: COL-031 | C91: =IFERROR(INDEX(Colaboradores!$E:$E,MATCH(B91,Colaboradores!$A:$A,0)),"") -> BELION FELIPE FERNANDES CORREIA | D91: DOC-040 | E91: =IFERROR(INDEX(Doc_Catalogo!$B:$B,MATCH(D91,Doc_Catalogo!$A:$A,0)),"") -> Ficha de EPI Atualizada | H91: =IF(G91="","N/A",IF(G91<TODAY(),"VENCIDO",IF(G91<=TODAY()+30,"VENCENDO","VALIDO"))) -> N/A | J91: Marcado como INDETERMINADO na planilha antiga (documento existe, sem data de vencimento fixa).
A92: REG-0091 | B92: COL-039 | C92: =IFERROR(INDEX(Colaboradores!$E:$E,MATCH(B92,Colaboradores!$A:$A,0)),"") -> PAULO CESAR ALVES DA SILVA | D92: DOC-001 | E92: =IFERROR(INDEX(Doc_Catalogo!$B:$B,MATCH(D92,Doc_Catalogo!$A:$A,0)),"") -> RG | G92: 48539 | H92: =IF(G92="","N/A",IF(G92<TODAY(),"VENCIDO",IF(G92<=TODAY()+30,"VENCENDO","VALIDO"))) -> VALIDO
A93: REG-0092 | B93: COL-039 | C93: =IFERROR(INDEX(Colaboradores!$E:$E,MATCH(B93,Colaboradores!$A:$A,0)),"") -> PAULO CESAR ALVES DA SILVA | D93: DOC-004 | E93: =IFERROR(INDEX(Doc_Catalogo!$B:$B,MATCH(D93,Doc_Catalogo!$A:$A,0)),"") -> ASO | G93: 46231 | H93: =IF(G93="","N/A",IF(G93<TODAY(),"VENCIDO",IF(G93<=TODAY()+30,"VENCENDO","VALIDO"))) -> VENCIDO
A94: REG-0093 | B94: COL-039 | C94: =IFERROR(INDEX(Colaboradores!$E:$E,MATCH(B94,Colaboradores!$A:$A,0)),"") -> PAULO CESAR ALVES DA SILVA | D94: DOC-009 | E94: =IFERROR(INDEX(Doc_Catalogo!$B:$B,MATCH(D94,Doc_Catalogo!$A:$A,0)),"") -> Certificado da NR06 — Colaborador | G94: 46183 | H94: =IF(G94="","N/A",IF(G94<TODAY(),"VENCIDO",IF(G94<=TODAY()+30,"VENCENDO","VALIDO"))) -> VENCIDO
A95: REG-0094 | B95: COL-039 | C95: =IFERROR(INDEX(Colaboradores!$E:$E,MATCH(B95,Colaboradores!$A:$A,0)),"") -> PAULO CESAR ALVES DA SILVA | D95: DOC-011 | E95: =IFERROR(INDEX(Doc_Catalogo!$B:$B,MATCH(D95,Doc_Catalogo!$A:$A,0)),"") -> Certificado da NR10 — Colaborador | G95: 46544 | H95: =IF(G95="","N/A",IF(G95<TODAY(),"VENCIDO",IF(G95<=TODAY()+30,"VENCENDO","VALIDO"))) -> VALIDO
A96: REG-0095 | B96: COL-039 | C96: =IFERROR(INDEX(Colaboradores!$E:$E,MATCH(B96,Colaboradores!$A:$A,0)),"") -> PAULO CESAR ALVES DA SILVA | D96: DOC-017 | E96: =IFERROR(INDEX(Doc_Catalogo!$B:$B,MATCH(D96,Doc_Catalogo!$A:$A,0)),"") -> Certificado da NR12 — Colaborador | G96: 46550 | H96: =IF(G96="","N/A",IF(G96<TODAY(),"VENCIDO",IF(G96<=TODAY()+30,"VENCENDO","VALIDO"))) -> VALIDO
A97: REG-0096 | B97: COL-039 | C97: =IFERROR(INDEX(Colaboradores!$E:$E,MATCH(B97,Colaboradores!$A:$A,0)),"") -> PAULO CESAR ALVES DA SILVA | D97: DOC-021 | E97: =IFERROR(INDEX(Doc_Catalogo!$B:$B,MATCH(D97,Doc_Catalogo!$A:$A,0)),"") -> Certificado da NR17 — Colaborador | G97: 46487 | H97: =IF(G97="","N/A",IF(G97<TODAY(),"VENCIDO",IF(G97<=TODAY()+30,"VENCENDO","VALIDO"))) -> VALIDO
A98: REG-0097 | B98: COL-039 | C98: =IFERROR(INDEX(Colaboradores!$E:$E,MATCH(B98,Colaboradores!$A:$A,0)),"") -> PAULO CESAR ALVES DA SILVA | D98: DOC-023 | E98: =IFERROR(INDEX(Doc_Catalogo!$B:$B,MATCH(D98,Doc_Catalogo!$A:$A,0)),"") -> Certificado da NR18 — Colaborador | G98: 46558 | H98: =IF(G98="","N/A",IF(G98<TODAY(),"VENCIDO",IF(G98<=TODAY()+30,"VENCENDO","VALIDO"))) -> VALIDO
A99: REG-0098 | B99: COL-039 | C99: =IFERROR(INDEX(Colaboradores!$E:$E,MATCH(B99,Colaboradores!$A:$A,0)),"") -> PAULO CESAR ALVES DA SILVA | D99: DOC-025 | E99: =IFERROR(INDEX(Doc_Catalogo!$B:$B,MATCH(D99,Doc_Catalogo!$A:$A,0)),"") -> Certificado da NR33 — Colaborador | G99: 46191 | H99: =IF(G99="","N/A",IF(G99<TODAY(),"VENCIDO",IF(G99<=TODAY()+30,"VENCENDO","VALIDO"))) -> VENCIDO
A100: REG-0099 | B100: COL-039 | C100: =IFERROR(INDEX(Colaboradores!$E:$E,MATCH(B100,Colaboradores!$A:$A,0)),"") -> PAULO CESAR ALVES DA SILVA | D100: DOC-031 | E100: =IFERROR(INDEX(Doc_Catalogo!$B:$B,MATCH(D100,Doc_Catalogo!$A:$A,0)),"") -> Certificado da NR35 — Colaborador | G100: 46554 | H100: =IF(G100="","N/A",IF(G100<TODAY(),"VENCIDO",IF(G100<=TODAY()+30,"VENCENDO","VALIDO"))) -> VALIDO
A101: REG-0100 | B101: COL-039 | C101: =IFERROR(INDEX(Colaboradores!$E:$E,MATCH(B101,Colaboradores!$A:$A,0)),"") -> PAULO CESAR ALVES DA SILVA | D101: DOC-039 | E101: =IFERROR(INDEX(Doc_Catalogo!$B:$B,MATCH(D101,Doc_Catalogo!$A:$A,0)),"") -> Ordem de Servico | H101: =IF(G101="","N/A",IF(G101<TODAY(),"VENCIDO",IF(G101<=TODAY()+30,"VENCENDO","VALIDO"))) -> N/A | J101: Marcado como INDETERMINADO na planilha antiga (documento existe, sem data de vencimento fixa).
...

Sheet Envios_Obra_Documento
A1: ID_Envio | B1: ID_Obra | C1: Nome_Obra | D1: Tipo_Origem | E1: ID_Empresa_ou_Colaborador | F1: Nome | G1: ID_Documento | H1: Nome_Documento | I1: Status_Exigencia | J1: Observacao
A2: ENV-0001 | B2: OBR-001 | C2: =IFERROR(INDEX(Obras!$B:$B,MATCH(B2,Obras!$A:$A,0)),"") -> Metro SP | D2: Empresa | E2: EMP-018 | F2: =IFERROR(INDEX(Empresas!$D:$D,MATCH(E2,Empresas!$A:$A,0)),"") -> OLIVER ELEVADORES LTDA | G2: DOC-051 | H2: =IFERROR(INDEX(Doc_Catalogo!$B:$B,MATCH(G2,Doc_Catalogo!$A:$A,0)),"") -> Contrato Social | I2: enviado
A3: ENV-0002 | B3: OBR-001 | C3: =IFERROR(INDEX(Obras!$B:$B,MATCH(B3,Obras!$A:$A,0)),"") -> Metro SP | D3: Empresa | E3: EMP-018 | F3: =IFERROR(INDEX(Empresas!$D:$D,MATCH(E3,Empresas!$A:$A,0)),"") -> OLIVER ELEVADORES LTDA | G3: DOC-052 | H3: =IFERROR(INDEX(Doc_Catalogo!$B:$B,MATCH(G3,Doc_Catalogo!$A:$A,0)),"") -> Inscricao Estadual / Municipal | I3: nao_aplicavel
A4: ENV-0003 | B4: OBR-001 | C4: =IFERROR(INDEX(Obras!$B:$B,MATCH(B4,Obras!$A:$A,0)),"") -> Metro SP | D4: Empresa | E4: EMP-018 | F4: =IFERROR(INDEX(Empresas!$D:$D,MATCH(E4,Empresas!$A:$A,0)),"") -> OLIVER ELEVADORES LTDA | G4: DOC-049 | H4: =IFERROR(INDEX(Doc_Catalogo!$B:$B,MATCH(G4,Doc_Catalogo!$A:$A,0)),"") -> PGR | I4: enviado
A5: ENV-0004 | B5: OBR-001 | C5: =IFERROR(INDEX(Obras!$B:$B,MATCH(B5,Obras!$A:$A,0)),"") -> Metro SP | D5: Empresa | E5: EMP-018 | F5: =IFERROR(INDEX(Empresas!$D:$D,MATCH(E5,Empresas!$A:$A,0)),"") -> OLIVER ELEVADORES LTDA | G5: DOC-050 | H5: =IFERROR(INDEX(Doc_Catalogo!$B:$B,MATCH(G5,Doc_Catalogo!$A:$A,0)),"") -> PCMSO | I5: enviado
A6: ENV-0005 | B6: OBR-001 | C6: =IFERROR(INDEX(Obras!$B:$B,MATCH(B6,Obras!$A:$A,0)),"") -> Metro SP | D6: Empresa | E6: EMP-018 | F6: =IFERROR(INDEX(Empresas!$D:$D,MATCH(E6,Empresas!$A:$A,0)),"") -> OLIVER ELEVADORES LTDA | G6: DOC-053 | H6: =IFERROR(INDEX(Doc_Catalogo!$B:$B,MATCH(G6,Doc_Catalogo!$A:$A,0)),"") -> APR — Analise Preliminar de Risco | I6: nao_aplicavel
A7: ENV-0006 | B7: OBR-001 | C7: =IFERROR(INDEX(Obras!$B:$B,MATCH(B7,Obras!$A:$A,0)),"") -> Metro SP | D7: Empresa | E7: EMP-018 | F7: =IFERROR(INDEX(Empresas!$D:$D,MATCH(E7,Empresas!$A:$A,0)),"") -> OLIVER ELEVADORES LTDA | G7: DOC-058 | H7: =IFERROR(INDEX(Doc_Catalogo!$B:$B,MATCH(G7,Doc_Catalogo!$A:$A,0)),"") -> Contrato de prestacao de servicos entre tomador e empreiteiro | I7: enviado
A8: ENV-0007 | B8: OBR-001 | C8: =IFERROR(INDEX(Obras!$B:$B,MATCH(B8,Obras!$A:$A,0)),"") -> Metro SP | D8: Colaborador | E8: COL-019 | F8: =IFERROR(INDEX(Colaboradores!$E:$E,MATCH(E8,Colaboradores!$A:$A,0)),"") -> ANDERSON DA SILVA | G8: DOC-034 | H8: =IFERROR(INDEX(Doc_Catalogo!$B:$B,MATCH(G8,Doc_Catalogo!$A:$A,0)),"") -> Ficha de Registro | I8: nao_aplicavel
A9: ENV-0008 | B9: OBR-001 | C9: =IFERROR(INDEX(Obras!$B:$B,MATCH(B9,Obras!$A:$A,0)),"") -> Metro SP | D9: Colaborador | E9: COL-020 | F9: =IFERROR(INDEX(Colaboradores!$E:$E,MATCH(E9,Colaboradores!$A:$A,0)),"") -> WALISON TANDI AZEVEDO DE OLIVEIRA MELO | G9: DOC-034 | H9: =IFERROR(INDEX(Doc_Catalogo!$B:$B,MATCH(G9,Doc_Catalogo!$A:$A,0)),"") -> Ficha de Registro | I9: nao_aplicavel
A10: ENV-0009 | B10: OBR-001 | C10: =IFERROR(INDEX(Obras!$B:$B,MATCH(B10,Obras!$A:$A,0)),"") -> Metro SP | D10: Colaborador | E10: COL-019 | F10: =IFERROR(INDEX(Colaboradores!$E:$E,MATCH(E10,Colaboradores!$A:$A,0)),"") -> ANDERSON DA SILVA | G10: DOC-036 | H10: =IFERROR(INDEX(Doc_Catalogo!$B:$B,MATCH(G10,Doc_Catalogo!$A:$A,0)),"") -> Contrato de Trabalho | I10: enviado
A11: ENV-0010 | B11: OBR-001 | C11: =IFERROR(INDEX(Obras!$B:$B,MATCH(B11,Obras!$A:$A,0)),"") -> Metro SP | D11: Colaborador | E11: COL-020 | F11: =IFERROR(INDEX(Colaboradores!$E:$E,MATCH(E11,Colaboradores!$A:$A,0)),"") -> WALISON TANDI AZEVEDO DE OLIVEIRA MELO | G11: DOC-036 | H11: =IFERROR(INDEX(Doc_Catalogo!$B:$B,MATCH(G11,Doc_Catalogo!$A:$A,0)),"") -> Contrato de Trabalho | I11: enviado
A12: ENV-0011 | B12: OBR-001 | C12: =IFERROR(INDEX(Obras!$B:$B,MATCH(B12,Obras!$A:$A,0)),"") -> Metro SP | D12: Colaborador | E12: COL-019 | F12: =IFERROR(INDEX(Colaboradores!$E:$E,MATCH(E12,Colaboradores!$A:$A,0)),"") -> ANDERSON DA SILVA | G12: DOC-038 | H12: =IFERROR(INDEX(Doc_Catalogo!$B:$B,MATCH(G12,Doc_Catalogo!$A:$A,0)),"") -> CTPS Digital | I12: nao_aplicavel
A13: ENV-0012 | B13: OBR-001 | C13: =IFERROR(INDEX(Obras!$B:$B,MATCH(B13,Obras!$A:$A,0)),"") -> Metro SP | D13: Colaborador | E13: COL-020 | F13: =IFERROR(INDEX(Colaboradores!$E:$E,MATCH(E13,Colaboradores!$A:$A,0)),"") -> WALISON TANDI AZEVEDO DE OLIVEIRA MELO | G13: DOC-038 | H13: =IFERROR(INDEX(Doc_Catalogo!$B:$B,MATCH(G13,Doc_Catalogo!$A:$A,0)),"") -> CTPS Digital | I13: nao_aplicavel
A14: ENV-0013 | B14: OBR-001 | C14: =IFERROR(INDEX(Obras!$B:$B,MATCH(B14,Obras!$A:$A,0)),"") -> Metro SP | D14: Colaborador | E14: COL-019 | F14: =IFERROR(INDEX(Colaboradores!$E:$E,MATCH(E14,Colaboradores!$A:$A,0)),"") -> ANDERSON DA SILVA | G14: DOC-001 | H14: =IFERROR(INDEX(Doc_Catalogo!$B:$B,MATCH(G14,Doc_Catalogo!$A:$A,0)),"") -> RG | I14: enviado
A15: ENV-0014 | B15: OBR-001 | C15: =IFERROR(INDEX(Obras!$B:$B,MATCH(B15,Obras!$A:$A,0)),"") -> Metro SP | D15: Colaborador | E15: COL-020 | F15: =IFERROR(INDEX(Colaboradores!$E:$E,MATCH(E15,Colaboradores!$A:$A,0)),"") -> WALISON TANDI AZEVEDO DE OLIVEIRA MELO | G15: DOC-001 | H15: =IFERROR(INDEX(Doc_Catalogo!$B:$B,MATCH(G15,Doc_Catalogo!$A:$A,0)),"") -> RG | I15: pendente | J15: Valor original na planilha antiga: 'CNH' (nao era um simples OK) — confirmar interpretacao.
A16: ENV-0015 | B16: OBR-001 | C16: =IFERROR(INDEX(Obras!$B:$B,MATCH(B16,Obras!$A:$A,0)),"") -> Metro SP | D16: Colaborador | E16: COL-019 | F16: =IFERROR(INDEX(Colaboradores!$E:$E,MATCH(E16,Colaboradores!$A:$A,0)),"") -> ANDERSON DA SILVA | G16: DOC-002 | H16: =IFERROR(INDEX(Doc_Catalogo!$B:$B,MATCH(G16,Doc_Catalogo!$A:$A,0)),"") -> CPF | I16: pendente | J16: Valor original na planilha antiga: 'CNH' (nao era um simples OK) — confirmar interpretacao.
A17: ENV-0016 | B17: OBR-001 | C17: =IFERROR(INDEX(Obras!$B:$B,MATCH(B17,Obras!$A:$A,0)),"") -> Metro SP | D17: Colaborador | E17: COL-020 | F17: =IFERROR(INDEX(Colaboradores!$E:$E,MATCH(E17,Colaboradores!$A:$A,0)),"") -> WALISON TANDI AZEVEDO DE OLIVEIRA MELO | G17: DOC-002 | H17: =IFERROR(INDEX(Doc_Catalogo!$B:$B,MATCH(G17,Doc_Catalogo!$A:$A,0)),"") -> CPF | I17: pendente | J17: Valor original na planilha antiga: 'CNH' (nao era um simples OK) — confirmar interpretacao.
A18: ENV-0017 | B18: OBR-001 | C18: =IFERROR(INDEX(Obras!$B:$B,MATCH(B18,Obras!$A:$A,0)),"") -> Metro SP | D18: Colaborador | E18: COL-019 | F18: =IFERROR(INDEX(Colaboradores!$E:$E,MATCH(E18,Colaboradores!$A:$A,0)),"") -> ANDERSON DA SILVA | G18: DOC-039 | H18: =IFERROR(INDEX(Doc_Catalogo!$B:$B,MATCH(G18,Doc_Catalogo!$A:$A,0)),"") -> Ordem de Servico | I18: enviado
A19: ENV-0018 | B19: OBR-001 | C19: =IFERROR(INDEX(Obras!$B:$B,MATCH(B19,Obras!$A:$A,0)),"") -> Metro SP | D19: Colaborador | E19: COL-020 | F19: =IFERROR(INDEX(Colaboradores!$E:$E,MATCH(E19,Colaboradores!$A:$A,0)),"") -> WALISON TANDI AZEVEDO DE OLIVEIRA MELO | G19: DOC-039 | H19: =IFERROR(INDEX(Doc_Catalogo!$B:$B,MATCH(G19,Doc_Catalogo!$A:$A,0)),"") -> Ordem de Servico | I19: enviado
A20: ENV-0019 | B20: OBR-001 | C20: =IFERROR(INDEX(Obras!$B:$B,MATCH(B20,Obras!$A:$A,0)),"") -> Metro SP | D20: Colaborador | E20: COL-019 | F20: =IFERROR(INDEX(Colaboradores!$E:$E,MATCH(E20,Colaboradores!$A:$A,0)),"") -> ANDERSON DA SILVA | G20: DOC-040 | H20: =IFERROR(INDEX(Doc_Catalogo!$B:$B,MATCH(G20,Doc_Catalogo!$A:$A,0)),"") -> Ficha de EPI Atualizada | I20: enviado
A21: ENV-0020 | B21: OBR-001 | C21: =IFERROR(INDEX(Obras!$B:$B,MATCH(B21,Obras!$A:$A,0)),"") -> Metro SP | D21: Colaborador | E21: COL-020 | F21: =IFERROR(INDEX(Colaboradores!$E:$E,MATCH(E21,Colaboradores!$A:$A,0)),"") -> WALISON TANDI AZEVEDO DE OLIVEIRA MELO | G21: DOC-040 | H21: =IFERROR(INDEX(Doc_Catalogo!$B:$B,MATCH(G21,Doc_Catalogo!$A:$A,0)),"") -> Ficha de EPI Atualizada | I21: enviado
A22: ENV-0021 | B22: OBR-001 | C22: =IFERROR(INDEX(Obras!$B:$B,MATCH(B22,Obras!$A:$A,0)),"") -> Metro SP | D22: Colaborador | E22: COL-019 | F22: =IFERROR(INDEX(Colaboradores!$E:$E,MATCH(E22,Colaboradores!$A:$A,0)),"") -> ANDERSON DA SILVA | G22: DOC-004 | H22: =IFERROR(INDEX(Doc_Catalogo!$B:$B,MATCH(G22,Doc_Catalogo!$A:$A,0)),"") -> ASO | I22: enviado
A23: ENV-0022 | B23: OBR-001 | C23: =IFERROR(INDEX(Obras!$B:$B,MATCH(B23,Obras!$A:$A,0)),"") -> Metro SP | D23: Colaborador | E23: COL-020 | F23: =IFERROR(INDEX(Colaboradores!$E:$E,MATCH(E23,Colaboradores!$A:$A,0)),"") -> WALISON TANDI AZEVEDO DE OLIVEIRA MELO | G23: DOC-004 | H23: =IFERROR(INDEX(Doc_Catalogo!$B:$B,MATCH(G23,Doc_Catalogo!$A:$A,0)),"") -> ASO | I23: enviado
A24: ENV-0023 | B24: OBR-001 | C24: =IFERROR(INDEX(Obras!$B:$B,MATCH(B24,Obras!$A:$A,0)),"") -> Metro SP | D24: Colaborador | E24: COL-019 | F24: =IFERROR(INDEX(Colaboradores!$E:$E,MATCH(E24,Colaboradores!$A:$A,0)),"") -> ANDERSON DA SILVA | G24: DOC-011 | H24: =IFERROR(INDEX(Doc_Catalogo!$B:$B,MATCH(G24,Doc_Catalogo!$A:$A,0)),"") -> Certificado da NR10 — Colaborador | I24: pendente
A25: ENV-0024 | B25: OBR-001 | C25: =IFERROR(INDEX(Obras!$B:$B,MATCH(B25,Obras!$A:$A,0)),"") -> Metro SP | D25: Colaborador | E25: COL-020 | F25: =IFERROR(INDEX(Colaboradores!$E:$E,MATCH(E25,Colaboradores!$A:$A,0)),"") -> WALISON TANDI AZEVEDO DE OLIVEIRA MELO | G25: DOC-011 | H25: =IFERROR(INDEX(Doc_Catalogo!$B:$B,MATCH(G25,Doc_Catalogo!$A:$A,0)),"") -> Certificado da NR10 — Colaborador | I25: enviado
A26: ENV-0025 | B26: OBR-001 | C26: =IFERROR(INDEX(Obras!$B:$B,MATCH(B26,Obras!$A:$A,0)),"") -> Metro SP | D26: Colaborador | E26: COL-019 | F26: =IFERROR(INDEX(Colaboradores!$E:$E,MATCH(E26,Colaboradores!$A:$A,0)),"") -> ANDERSON DA SILVA | G26: DOC-017 | H26: =IFERROR(INDEX(Doc_Catalogo!$B:$B,MATCH(G26,Doc_Catalogo!$A:$A,0)),"") -> Certificado da NR12 — Colaborador | I26: enviado
A27: ENV-0026 | B27: OBR-001 | C27: =IFERROR(INDEX(Obras!$B:$B,MATCH(B27,Obras!$A:$A,0)),"") -> Metro SP | D27: Colaborador | E27: COL-020 | F27: =IFERROR(INDEX(Colaboradores!$E:$E,MATCH(E27,Colaboradores!$A:$A,0)),"") -> WALISON TANDI AZEVEDO DE OLIVEIRA MELO | G27: DOC-017 | H27: =IFERROR(INDEX(Doc_Catalogo!$B:$B,MATCH(G27,Doc_Catalogo!$A:$A,0)),"") -> Certificado da NR12 — Colaborador | I27: enviado
A28: ENV-0027 | B28: OBR-001 | C28: =IFERROR(INDEX(Obras!$B:$B,MATCH(B28,Obras!$A:$A,0)),"") -> Metro SP | D28: Colaborador | E28: COL-019 | F28: =IFERROR(INDEX(Colaboradores!$E:$E,MATCH(E28,Colaboradores!$A:$A,0)),"") -> ANDERSON DA SILVA | G28: DOC-023 | H28: =IFERROR(INDEX(Doc_Catalogo!$B:$B,MATCH(G28,Doc_Catalogo!$A:$A,0)),"") -> Certificado da NR18 — Colaborador | I28: enviado
A29: ENV-0028 | B29: OBR-001 | C29: =IFERROR(INDEX(Obras!$B:$B,MATCH(B29,Obras!$A:$A,0)),"") -> Metro SP | D29: Colaborador | E29: COL-020 | F29: =IFERROR(INDEX(Colaboradores!$E:$E,MATCH(E29,Colaboradores!$A:$A,0)),"") -> WALISON TANDI AZEVEDO DE OLIVEIRA MELO | G29: DOC-023 | H29: =IFERROR(INDEX(Doc_Catalogo!$B:$B,MATCH(G29,Doc_Catalogo!$A:$A,0)),"") -> Certificado da NR18 — Colaborador | I29: enviado
... A40: ENV-0039 | B40: OBR-002 | C40: =IFERROR(INDEX(Obras!$B:$B,MATCH(B40,Obras!$A:$A,0)),"") -> Metro BH | D40: Colaborador | E40: COL-030 | F40: =IFERROR(INDEX(Colaboradores!$E:$E,MATCH(E40,Colaboradores!$A:$A,0)),"") -> AVANY MAIA DOS REIS | G40: DOC-009 | H40: =IFERROR(INDEX(Doc_Catalogo!$B:$B,MATCH(G40,Doc_Catalogo!$A:$A,0)),"") -> Certificado da NR06 — Colaborador | I40: enviado
A41: ENV-0040 | B41: OBR-002 | C41: =IFERROR(INDEX(Obras!$B:$B,MATCH(B41,Obras!$A:$A,0)),"") -> Metro BH | D41: Colaborador | E41: COL-030 | F41: =IFERROR(INDEX(Colaboradores!$E:$E,MATCH(E41,Colaboradores!$A:$A,0)),"") -> AVANY MAIA DOS REIS | G41: DOC-038 | H41: =IFERROR(INDEX(Doc_Catalogo!$B:$B,MATCH(G41,Doc_Catalogo!$A:$A,0)),"") -> CTPS Digital | I41: pendente | J41: Valor original na planilha antiga: 'E-social' (nao era um simples OK) — confirmar interpretacao.
A42: ENV-0041 | B42: OBR-002 | C42: =IFERROR(INDEX(Obras!$B:$B,MATCH(B42,Obras!$A:$A,0)),"") -> Metro BH | D42: Colaborador | E42: COL-030 | F42: =IFERROR(INDEX(Colaboradores!$E:$E,MATCH(E42,Colaboradores!$A:$A,0)),"") -> AVANY MAIA DOS REIS | G42: DOC-034 | H42: =IFERROR(INDEX(Doc_Catalogo!$B:$B,MATCH(G42,Doc_Catalogo!$A:$A,0)),"") -> Ficha de Registro | I42: enviado
A43: ENV-0042 | B43: OBR-002 | C43: =IFERROR(INDEX(Obras!$B:$B,MATCH(B43,Obras!$A:$A,0)),"") -> Metro BH | D43: Colaborador | E43: COL-030 | F43: =IFERROR(INDEX(Colaboradores!$E:$E,MATCH(E43,Colaboradores!$A:$A,0)),"") -> AVANY MAIA DOS REIS | G43: DOC-011 | H43: =IFERROR(INDEX(Doc_Catalogo!$B:$B,MATCH(G43,Doc_Catalogo!$A:$A,0)),"") -> Certificado da NR10 — Colaborador | I43: enviado
A44: ENV-0043 | B44: OBR-002 | C44: =IFERROR(INDEX(Obras!$B:$B,MATCH(B44,Obras!$A:$A,0)),"") -> Metro BH | D44: Colaborador | E44: COL-030 | F44: =IFERROR(INDEX(Colaboradores!$E:$E,MATCH(E44,Colaboradores!$A:$A,0)),"") -> AVANY MAIA DOS REIS | G44: DOC-015 | H44: =IFERROR(INDEX(Doc_Catalogo!$B:$B,MATCH(G44,Doc_Catalogo!$A:$A,0)),"") -> Certificado da NR11 — Colaborador | I44: pendente
A45: ENV-0044 | B45: OBR-002 | C45: =IFERROR(INDEX(Obras!$B:$B,MATCH(B45,Obras!$A:$A,0)),"") -> Metro BH | D45: Colaborador | E45: COL-030 | F45: =IFERROR(INDEX(Colaboradores!$E:$E,MATCH(E45,Colaboradores!$A:$A,0)),"") -> AVANY MAIA DOS REIS | G45: DOC-017 | H45: =IFERROR(INDEX(Doc_Catalogo!$B:$B,MATCH(G45,Doc_Catalogo!$A:$A,0)),"") -> Certificado da NR12 — Colaborador | I45: enviado
A46: ENV-0045 | B46: OBR-002 | C46: =IFERROR(INDEX(Obras!$B:$B,MATCH(B46,Obras!$A:$A,0)),"") -> Metro BH | D46: Colaborador | E46: COL-030 | F46: =IFERROR(INDEX(Colaboradores!$E:$E,MATCH(E46,Colaboradores!$A:$A,0)),"") -> AVANY MAIA DOS REIS | G46: DOC-023 | H46: =IFERROR(INDEX(Doc_Catalogo!$B:$B,MATCH(G46,Doc_Catalogo!$A:$A,0)),"") -> Certificado da NR18 — Colaborador | I46: enviado
A47: ENV-0046 | B47: OBR-002 | C47: =IFERROR(INDEX(Obras!$B:$B,MATCH(B47,Obras!$A:$A,0)),"") -> Metro BH | D47: Colaborador | E47: COL-030 | F47: =IFERROR(INDEX(Colaboradores!$E:$E,MATCH(E47,Colaboradores!$A:$A,0)),"") -> AVANY MAIA DOS REIS | G47: DOC-025 | H47: =IFERROR(INDEX(Doc_Catalogo!$B:$B,MATCH(G47,Doc_Catalogo!$A:$A,0)),"") -> Certificado da NR33 — Colaborador | I47: enviado
A48: ENV-0047 | B48: OBR-002 | C48: =IFERROR(INDEX(Obras!$B:$B,MATCH(B48,Obras!$A:$A,0)),"") -> Metro BH | D48: Colaborador | E48: COL-030 | F48: =IFERROR(INDEX(Colaboradores!$E:$E,MATCH(E48,Colaboradores!$A:$A,0)),"") -> AVANY MAIA DOS REIS | G48: DOC-031 | H48: =IFERROR(INDEX(Doc_Catalogo!$B:$B,MATCH(G48,Doc_Catalogo!$A:$A,0)),"") -> Certificado da NR35 — Colaborador | I48: enviado
A49: ENV-0048 | B49: OBR-002 | C49: =IFERROR(INDEX(Obras!$B:$B,MATCH(B49,Obras!$A:$A,0)),"") -> Metro BH | D49: Colaborador | E49: COL-033 | F49: =IFERROR(INDEX(Colaboradores!$E:$E,MATCH(E49,Colaboradores!$A:$A,0)),"") -> DANIEL APARECIDO DOS REIS FELICIANO | G49: DOC-004 | H49: =IFERROR(INDEX(Doc_Catalogo!$B:$B,MATCH(G49,Doc_Catalogo!$A:$A,0)),"") -> ASO | I49: enviado
A50: ENV-0049 | B50: OBR-002 | C50: =IFERROR(INDEX(Obras!$B:$B,MATCH(B50,Obras!$A:$A,0)),"") -> Metro BH | D50: Colaborador | E50: COL-033 | F50: =IFERROR(INDEX(Colaboradores!$E:$E,MATCH(E50,Colaboradores!$A:$A,0)),"") -> DANIEL APARECIDO DOS REIS FELICIANO | G50: DOC-039 | H50: =IFERROR(INDEX(Doc_Catalogo!$B:$B,MATCH(G50,Doc_Catalogo!$A:$A,0)),"") -> Ordem de Servico | I50: enviado
A51: ENV-0050 | B51: OBR-002 | C51: =IFERROR(INDEX(Obras!$B:$B,MATCH(B51,Obras!$A:$A,0)),"") -> Metro BH | D51: Colaborador | E51: COL-033 | F51: =IFERROR(INDEX(Colaboradores!$E:$E,MATCH(E51,Colaboradores!$A:$A,0)),"") -> DANIEL APARECIDO DOS REIS FELICIANO | G51: DOC-040 | H51: =IFERROR(INDEX(Doc_Catalogo!$B:$B,MATCH(G51,Doc_Catalogo!$A:$A,0)),"") -> Ficha de EPI Atualizada | I51: enviado
A52: ENV-0051 | B52: OBR-002 | C52: =IFERROR(INDEX(Obras!$B:$B,MATCH(B52,Obras!$A:$A,0)),"") -> Metro BH | D52: Colaborador | E52: COL-033 | F52: =IFERROR(INDEX(Colaboradores!$E:$E,MATCH(E52,Colaboradores!$A:$A,0)),"") -> DANIEL APARECIDO DOS REIS FELICIANO | G52: DOC-007 | H52: =IFERROR(INDEX(Doc_Catalogo!$B:$B,MATCH(G52,Doc_Catalogo!$A:$A,0)),"") -> Certificado da NR01 — Colaborador | I52: pendente
A53: ENV-0052 | B53: OBR-002 | C53: =IFERROR(INDEX(Obras!$B:$B,MATCH(B53,Obras!$A:$A,0)),"") -> Metro BH | D53: Colaborador | E53: COL-033 | F53: =IFERROR(INDEX(Colaboradores!$E:$E,MATCH(E53,Colaboradores!$A:$A,0)),"") -> DANIEL APARECIDO DOS REIS FELICIANO | G53: DOC-009 | H53: =IFERROR(INDEX(Doc_Catalogo!$B:$B,MATCH(G53,Doc_Catalogo!$A:$A,0)),"") -> Certificado da NR06 — Colaborador | I53: enviado
A54: ENV-0053 | B54: OBR-002 | C54: =IFERROR(INDEX(Obras!$B:$B,MATCH(B54,Obras!$A:$A,0)),"") -> Metro BH | D54: Colaborador | E54: COL-033 | F54: =IFERROR(INDEX(Colaboradores!$E:$E,MATCH(E54,Colaboradores!$A:$A,0)),"") -> DANIEL APARECIDO DOS REIS FELICIANO | G54: DOC-038 | H54: =IFERROR(INDEX(Doc_Catalogo!$B:$B,MATCH(G54,Doc_Catalogo!$A:$A,0)),"") -> CTPS Digital | I54: pendente | J54: Valor original na planilha antiga: 'E-social' (nao era um simples OK) — confirmar interpretacao.
A55: ENV-0054 | B55: OBR-002 | C55: =IFERROR(INDEX(Obras!$B:$B,MATCH(B55,Obras!$A:$A,0)),"") -> Metro BH | D55: Colaborador | E55: COL-033 | F55: =IFERROR(INDEX(Colaboradores!$E:$E,MATCH(E55,Colaboradores!$A:$A,0)),"") -> DANIEL APARECIDO DOS REIS FELICIANO | G55: DOC-034 | H55: =IFERROR(INDEX(Doc_Catalogo!$B:$B,MATCH(G55,Doc_Catalogo!$A:$A,0)),"") -> Ficha de Registro | I55: enviado
A56: ENV-0055 | B56: OBR-002 | C56: =IFERROR(INDEX(Obras!$B:$B,MATCH(B56,Obras!$A:$A,0)),"") -> Metro BH | D56: Colaborador | E56: COL-033 | F56: =IFERROR(INDEX(Colaboradores!$E:$E,MATCH(E56,Colaboradores!$A:$A,0)),"") -> DANIEL APARECIDO DOS REIS FELICIANO | G56: DOC-011 | H56: =IFERROR(INDEX(Doc_Catalogo!$B:$B,MATCH(G56,Doc_Catalogo!$A:$A,0)),"") -> Certificado da NR10 — Colaborador | I56: enviado
A57: ENV-0056 | B57: OBR-002 | C57: =IFERROR(INDEX(Obras!$B:$B,MATCH(B57,Obras!$A:$A,0)),"") -> Metro BH | D57: Colaborador | E57: COL-033 | F57: =IFERROR(INDEX(Colaboradores!$E:$E,MATCH(E57,Colaboradores!$A:$A,0)),"") -> DANIEL APARECIDO DOS REIS FELICIANO | G57: DOC-015 | H57: =IFERROR(INDEX(Doc_Catalogo!$B:$B,MATCH(G57,Doc_Catalogo!$A:$A,0)),"") -> Certificado da NR11 — Colaborador | I57: pendente
A58: ENV-0057 | B58: OBR-002 | C58: =IFERROR(INDEX(Obras!$B:$B,MATCH(B58,Obras!$A:$A,0)),"") -> Metro BH | D58: Colaborador | E58: COL-033 | F58: =IFERROR(INDEX(Colaboradores!$E:$E,MATCH(E58,Colaboradores!$A:$A,0)),"") -> DANIEL APARECIDO DOS REIS FELICIANO | G58: DOC-017 | H58: =IFERROR(INDEX(Doc_Catalogo!$B:$B,MATCH(G58,Doc_Catalogo!$A:$A,0)),"") -> Certificado da NR12 — Colaborador | I58: enviado
A59: ENV-0058 | B59: OBR-002 | C59: =IFERROR(INDEX(Obras!$B:$B,MATCH(B59,Obras!$A:$A,0)),"") -> Metro BH | D59: Colaborador | E59: COL-033 | F59: =IFERROR(INDEX(Colaboradores!$E:$E,MATCH(E59,Colaboradores!$A:$A,0)),"") -> DANIEL APARECIDO DOS REIS FELICIANO | G59: DOC-023 | H59: =IFERROR(INDEX(Doc_Catalogo!$B:$B,MATCH(G59,Doc_Catalogo!$A:$A,0)),"") -> Certificado da NR18 — Colaborador | I59: enviado
A60: ENV-0059 | B60: OBR-002 | C60: =IFERROR(INDEX(Obras!$B:$B,MATCH(B60,Obras!$A:$A,0)),"") -> Metro BH | D60: Colaborador | E60: COL-033 | F60: =IFERROR(INDEX(Colaboradores!$E:$E,MATCH(E60,Colaboradores!$A:$A,0)),"") -> DANIEL APARECIDO DOS REIS FELICIANO | G60: DOC-025 | H60: =IFERROR(INDEX(Doc_Catalogo!$B:$B,MATCH(G60,Doc_Catalogo!$A:$A,0)),"") -> Certificado da NR33 — Colaborador | I60: pendente
A61: ENV-0060 | B61: OBR-002 | C61: =IFERROR(INDEX(Obras!$B:$B,MATCH(B61,Obras!$A:$A,0)),"") -> Metro BH | D61: Colaborador | E61: COL-033 | F61: =IFERROR(INDEX(Colaboradores!$E:$E,MATCH(E61,Colaboradores!$A:$A,0)),"") -> DANIEL APARECIDO DOS REIS FELICIANO | G61: DOC-031 | H61: =IFERROR(INDEX(Doc_Catalogo!$B:$B,MATCH(G61,Doc_Catalogo!$A:$A,0)),"") -> Certificado da NR35 — Colaborador | I61: enviado
A62: ENV-0061 | B62: OBR-002 | C62: =IFERROR(INDEX(Obras!$B:$B,MATCH(B62,Obras!$A:$A,0)),"") -> Metro BH | D62: Colaborador | E62: COL-039 | F62: =IFERROR(INDEX(Colaboradores!$E:$E,MATCH(E62,Colaboradores!$A:$A,0)),"") -> PAULO CESAR ALVES DA SILVA | G62: DOC-004 | H62: =IFERROR(INDEX(Doc_Catalogo!$B:$B,MATCH(G62,Doc_Catalogo!$A:$A,0)),"") -> ASO | I62: enviado
A63: ENV-0062 | B63: OBR-002 | C63: =IFERROR(INDEX(Obras!$B:$B,MATCH(B63,Obras!$A:$A,0)),"") -> Metro BH | D63: Colaborador | E63: COL-039 | F63: =IFERROR(INDEX(Colaboradores!$E:$E,MATCH(E63,Colaboradores!$A:$A,0)),"") -> PAULO CESAR ALVES DA SILVA | G63: DOC-039 | H63: =IFERROR(INDEX(Doc_Catalogo!$B:$B,MATCH(G63,Doc_Catalogo!$A:$A,0)),"") -> Ordem de Servico | I63: enviado
A64: ENV-0063 | B64: OBR-002 | C64: =IFERROR(INDEX(Obras!$B:$B,MATCH(B64,Obras!$A:$A,0)),"") -> Metro BH | D64: Colaborador | E64: COL-039 | F64: =IFERROR(INDEX(Colaboradores!$E:$E,MATCH(E64,Colaboradores!$A:$A,0)),"") -> PAULO CESAR ALVES DA SILVA | G64: DOC-040 | H64: =IFERROR(INDEX(Doc_Catalogo!$B:$B,MATCH(G64,Doc_Catalogo!$A:$A,0)),"") -> Ficha de EPI Atualizada | I64: enviado
A65: ENV-0064 | B65: OBR-002 | C65: =IFERROR(INDEX(Obras!$B:$B,MATCH(B65,Obras!$A:$A,0)),"") -> Metro BH | D65: Colaborador | E65: COL-039 | F65: =IFERROR(INDEX(Colaboradores!$E:$E,MATCH(E65,Colaboradores!$A:$A,0)),"") -> PAULO CESAR ALVES DA SILVA | G65: DOC-007 | H65: =IFERROR(INDEX(Doc_Catalogo!$B:$B,MATCH(G65,Doc_Catalogo!$A:$A,0)),"") -> Certificado da NR01 — Colaborador | I65: pendente
A66: ENV-0065 | B66: OBR-002 | C66: =IFERROR(INDEX(Obras!$B:$B,MATCH(B66,Obras!$A:$A,0)),"") -> Metro BH | D66: Colaborador | E66: COL-039 | F66: =IFERROR(INDEX(Colaboradores!$E:$E,MATCH(E66,Colaboradores!$A:$A,0)),"") -> PAULO CESAR ALVES DA SILVA | G66: DOC-009 | H66: =IFERROR(INDEX(Doc_Catalogo!$B:$B,MATCH(G66,Doc_Catalogo!$A:$A,0)),"") -> Certificado da NR06 — Colaborador | I66: enviado
... A87: ENV-0086 | B87: OBR-002 | C87: =IFERROR(INDEX(Obras!$B:$B,MATCH(B87,Obras!$A:$A,0)),"") -> Metro BH | D87: Colaborador | E87: COL-040 | F87: =IFERROR(INDEX(Colaboradores!$E:$E,MATCH(E87,Colaboradores!$A:$A,0)),"") -> YOANDERSON COSTA DOS SANTOS | G87: DOC-031 | H87: =IFERROR(INDEX(Doc_Catalogo!$B:$B,MATCH(G87,Doc_Catalogo!$A:$A,0)),"") -> Certificado da NR35 — Colaborador | I87: enviado
A88: ENV-0087 | B88: OBR-003 | C88: =IFERROR(INDEX(Obras!$B:$B,MATCH(B88,Obras!$A:$A,0)),"") -> Hospital SC | D88: Empresa | E88: EMP-002 | F88: =IFERROR(INDEX(Empresas!$D:$D,MATCH(E88,Empresas!$A:$A,0)),"") -> 60.536.286 SILVIO SCHURT | G88: DOC-058 | H88: =IFERROR(INDEX(Doc_Catalogo!$B:$B,MATCH(G88,Doc_Catalogo!$A:$A,0)),"") -> Contrato de prestacao de servicos entre tomador e empreiteiro | I88: pendente | J88: Valor original na planilha antiga: 'Contrato com a DHS' (nao era um simples OK) — confirmar interpretacao.
A89: ENV-0088 | B89: OBR-003 | C89: =IFERROR(INDEX(Obras!$B:$B,MATCH(B89,Obras!$A:$A,0)),"") -> Hospital SC | D89: Empresa | E89: EMP-003 | F89: =IFERROR(INDEX(Empresas!$D:$D,MATCH(E89,Empresas!$A:$A,0)),"") -> 60.555.952 GABRIEL SCHURT | G89: DOC-058 | H89: =IFERROR(INDEX(Doc_Catalogo!$B:$B,MATCH(G89,Doc_Catalogo!$A:$A,0)),"") -> Contrato de prestacao de servicos entre tomador e empreiteiro | I89: pendente | J89: Valor original na planilha antiga: 'Contrato com a DHS' (nao era um simples OK) — confirmar interpretacao.
A90: ENV-0089 | B90: OBR-003 | C90: =IFERROR(INDEX(Obras!$B:$B,MATCH(B90,Obras!$A:$A,0)),"") -> Hospital SC | D90: Empresa | E90: EMP-002 | F90: =IFERROR(INDEX(Empresas!$D:$D,MATCH(E90,Empresas!$A:$A,0)),"") -> 60.536.286 SILVIO SCHURT | G90: DOC-049 | H90: =IFERROR(INDEX(Doc_Catalogo!$B:$B,MATCH(G90,Doc_Catalogo!$A:$A,0)),"") -> PGR | I90: enviado
A91: ENV-0090 | B91: OBR-003 | C91: =IFERROR(INDEX(Obras!$B:$B,MATCH(B91,Obras!$A:$A,0)),"") -> Hospital SC | D91: Empresa | E91: EMP-006 | F91: =IFERROR(INDEX(Empresas!$D:$D,MATCH(E91,Empresas!$A:$A,0)),"") -> DHS ELEVADORES LTDA | G91: DOC-049 | H91: =IFERROR(INDEX(Doc_Catalogo!$B:$B,MATCH(G91,Doc_Catalogo!$A:$A,0)),"") -> PGR | I91: enviado
A92: ENV-0091 | B92: OBR-003 | C92: =IFERROR(INDEX(Obras!$B:$B,MATCH(B92,Obras!$A:$A,0)),"") -> Hospital SC | D92: Empresa | E92: EMP-003 | F92: =IFERROR(INDEX(Empresas!$D:$D,MATCH(E92,Empresas!$A:$A,0)),"") -> 60.555.952 GABRIEL SCHURT | G92: DOC-049 | H92: =IFERROR(INDEX(Doc_Catalogo!$B:$B,MATCH(G92,Doc_Catalogo!$A:$A,0)),"") -> PGR | I92: enviado
A93: ENV-0092 | B93: OBR-003 | C93: =IFERROR(INDEX(Obras!$B:$B,MATCH(B93,Obras!$A:$A,0)),"") -> Hospital SC | D93: Empresa | E93: EMP-017 | F93: =IFERROR(INDEX(Empresas!$D:$D,MATCH(E93,Empresas!$A:$A,0)),"") -> NEXT FLOOR LTDA | G93: DOC-049 | H93: =IFERROR(INDEX(Doc_Catalogo!$B:$B,MATCH(G93,Doc_Catalogo!$A:$A,0)),"") -> PGR | I93: enviado
A94: ENV-0093 | B94: OBR-003 | C94: =IFERROR(INDEX(Obras!$B:$B,MATCH(B94,Obras!$A:$A,0)),"") -> Hospital SC | D94: Empresa | E94: EMP-002 | F94: =IFERROR(INDEX(Empresas!$D:$D,MATCH(E94,Empresas!$A:$A,0)),"") -> 60.536.286 SILVIO SCHURT | G94: DOC-050 | H94: =IFERROR(INDEX(Doc_Catalogo!$B:$B,MATCH(G94,Doc_Catalogo!$A:$A,0)),"") -> PCMSO | I94: enviado
A95: ENV-0094 | B95: OBR-003 | C95: =IFERROR(INDEX(Obras!$B:$B,MATCH(B95,Obras!$A:$A,0)),"") -> Hospital SC | D95: Empresa | E95: EMP-006 | F95: =IFERROR(INDEX(Empresas!$D:$D,MATCH(E95,Empresas!$A:$A,0)),"") -> DHS ELEVADORES LTDA | G95: DOC-050 | H95: =IFERROR(INDEX(Doc_Catalogo!$B:$B,MATCH(G95,Doc_Catalogo!$A:$A,0)),"") -> PCMSO | I95: enviado
A96: ENV-0095 | B96: OBR-003 | C96: =IFERROR(INDEX(Obras!$B:$B,MATCH(B96,Obras!$A:$A,0)),"") -> Hospital SC | D96: Empresa | E96: EMP-003 | F96: =IFERROR(INDEX(Empresas!$D:$D,MATCH(E96,Empresas!$A:$A,0)),"") -> 60.555.952 GABRIEL SCHURT | G96: DOC-050 | H96: =IFERROR(INDEX(Doc_Catalogo!$B:$B,MATCH(G96,Doc_Catalogo!$A:$A,0)),"") -> PCMSO | I96: enviado
A97: ENV-0096 | B97: OBR-003 | C97: =IFERROR(INDEX(Obras!$B:$B,MATCH(B97,Obras!$A:$A,0)),"") -> Hospital SC | D97: Empresa | E97: EMP-017 | F97: =IFERROR(INDEX(Empresas!$D:$D,MATCH(E97,Empresas!$A:$A,0)),"") -> NEXT FLOOR LTDA | G97: DOC-050 | H97: =IFERROR(INDEX(Doc_Catalogo!$B:$B,MATCH(G97,Doc_Catalogo!$A:$A,0)),"") -> PCMSO | I97: enviado
A98: ENV-0097 | B98: OBR-003 | C98: =IFERROR(INDEX(Obras!$B:$B,MATCH(B98,Obras!$A:$A,0)),"") -> Hospital SC | D98: Empresa | E98: EMP-024 | F98: =IFERROR(INDEX(Empresas!$D:$D,MATCH(E98,Empresas!$A:$A,0)),"") -> VERTICAL TECH ELEVADORES LTDA | G98: DOC-050 | H98: =IFERROR(INDEX(Doc_Catalogo!$B:$B,MATCH(G98,Doc_Catalogo!$A:$A,0)),"") -> PCMSO | I98: enviado
A99: ENV-0098 | B99: OBR-003 | C99: =IFERROR(INDEX(Obras!$B:$B,MATCH(B99,Obras!$A:$A,0)),"") -> Hospital SC | D99: Empresa | E99: EMP-002 | F99: =IFERROR(INDEX(Empresas!$D:$D,MATCH(E99,Empresas!$A:$A,0)),"") -> 60.536.286 SILVIO SCHURT | G99: DOC-005 | H99: =IFERROR(INDEX(Doc_Catalogo!$B:$B,MATCH(G99,Doc_Catalogo!$A:$A,0)),"") -> CNPJ (situacao cadastral) | I99: enviado
A100: ENV-0099 | B100: OBR-003 | C100: =IFERROR(INDEX(Obras!$B:$B,MATCH(B100,Obras!$A:$A,0)),"") -> Hospital SC | D100: Empresa | E100: EMP-006 | F100: =IFERROR(INDEX(Empresas!$D:$D,MATCH(E100,Empresas!$A:$A,0)),"") -> DHS ELEVADORES LTDA | G100: DOC-005 | H100: =IFERROR(INDEX(Doc_Catalogo!$B:$B,MATCH(G100,Doc_Catalogo!$A:$A,0)),"") -> CNPJ (situacao cadastral) | I100: enviado
A101: ENV-0100 | B101: OBR-003 | C101: =IFERROR(INDEX(Obras!$B:$B,MATCH(B101,Obras!$A:$A,0)),"") -> Hospital SC | D101: Empresa | E101: EMP-003 | F101: =IFERROR(INDEX(Empresas!$D:$D,MATCH(E101,Empresas!$A:$A,0)),"") -> 60.555.952 GABRIEL SCHURT | G101: DOC-005 | H101: =IFERROR(INDEX(Doc_Catalogo!$B:$B,MATCH(G101,Doc_Catalogo!$A:$A,0)),"") -> CNPJ (situacao cadastral) | I101: enviado
... A160: ENV-0159 | B160: OBR-003 | C160: =IFERROR(INDEX(Obras!$B:$B,MATCH(B160,Obras!$A:$A,0)),"") -> Hospital SC | D160: Empresa | E160: EMP-003 | F160: =IFERROR(INDEX(Empresas!$D:$D,MATCH(E160,Empresas!$A:$A,0)),"") -> 60.555.952 GABRIEL SCHURT | G160: DOC-077 | H160: =IFERROR(INDEX(Doc_Catalogo!$B:$B,MATCH(G160,Doc_Catalogo!$A:$A,0)),"") -> CNDT — Certidao Negativa de Debitos Trabalhistas | I160: enviado
A161: ENV-0160 | B161: OBR-003 | C161: =IFERROR(INDEX(Obras!$B:$B,MATCH(B161,Obras!$A:$A,0)),"") -> Hospital SC | D161: Colaborador | E161: COL-002 | F161: =IFERROR(INDEX(Colaboradores!$E:$E,MATCH(E161,Colaboradores!$A:$A,0)),"") -> SILVIO SCHURT | G161: DOC-043 | H161: =IFERROR(INDEX(Doc_Catalogo!$B:$B,MATCH(G161,Doc_Catalogo!$A:$A,0)),"") -> Documento com foto (RG ou CNH apresentado) | I161: pendente | J161: Valor original na planilha antiga: 'CNH' (nao era um simples OK) — confirmar interpretacao.
A162: ENV-0161 | B162: OBR-003 | C162: =IFERROR(INDEX(Obras!$B:$B,MATCH(B162,Obras!$A:$A,0)),"") -> Hospital SC | D162: Colaborador | E162: COL-008 | F162: =IFERROR(INDEX(Colaboradores!$E:$E,MATCH(E162,Colaboradores!$A:$A,0)),"") -> DANIEL SCHURT | G162: DOC-043 | H162: =IFERROR(INDEX(Doc_Catalogo!$B:$B,MATCH(G162,Doc_Catalogo!$A:$A,0)),"") -> Documento com foto (RG ou CNH apresentado) | I162: pendente | J162: Valor original na planilha antiga: 'CNH' (nao era um simples OK) — confirmar interpretacao.
A163: ENV-0162 | B163: OBR-003 | C163: =IFERROR(INDEX(Obras!$B:$B,MATCH(B163,Obras!$A:$A,0)),"") -> Hospital SC | D163: Colaborador | E163: COL-041 | F163: =IFERROR(INDEX(Colaboradores!$E:$E,MATCH(E163,Colaboradores!$A:$A,0)),"") -> GABRIEL SCHURT (proprietario) | G163: DOC-043 | H163: =IFERROR(INDEX(Doc_Catalogo!$B:$B,MATCH(G163,Doc_Catalogo!$A:$A,0)),"") -> Documento com foto (RG ou CNH apresentado) | I163: pendente | J163: Valor original na planilha antiga: 'CNH' (nao era um simples OK) — confirmar interpretacao.
A164: ENV-0163 | B164: OBR-003 | C164: =IFERROR(INDEX(Obras!$B:$B,MATCH(B164,Obras!$A:$A,0)),"") -> Hospital SC | D164: Colaborador | E164: COL-018 | F164: =IFERROR(INDEX(Colaboradores!$E:$E,MATCH(E164,Colaboradores!$A:$A,0)),"") -> FABIO LEANDRO DE FREITAS ASSIS | G164: DOC-043 | H164: =IFERROR(INDEX(Doc_Catalogo!$B:$B,MATCH(G164,Doc_Catalogo!$A:$A,0)),"") -> Documento com foto (RG ou CNH apresentado) | I164: pendente | J164: Valor original na planilha antiga: 'CNH' (nao era um simples OK) — confirmar interpretacao.
A165: ENV-0164 | B165: OBR-003 | C165: =IFERROR(INDEX(Obras!$B:$B,MATCH(B165,Obras!$A:$A,0)),"") -> Hospital SC | D165: Colaborador | E165: COL-002 | F165: =IFERROR(INDEX(Colaboradores!$E:$E,MATCH(E165,Colaboradores!$A:$A,0)),"") -> SILVIO SCHURT | G165: DOC-044 | H165: =IFERROR(INDEX(Doc_Catalogo!$B:$B,MATCH(G165,Doc_Catalogo!$A:$A,0)),"") -> Comprovante de Residencia | I165: enviado
A166: ENV-0165 | B166: OBR-003 | C166: =IFERROR(INDEX(Obras!$B:$B,MATCH(B166,Obras!$A:$A,0)),"") -> Hospital SC | D166: Colaborador | E166: COL-008 | F166: =IFERROR(INDEX(Colaboradores!$E:$E,MATCH(E166,Colaboradores!$A:$A,0)),"") -> DANIEL SCHURT | G166: DOC-044 | H166: =IFERROR(INDEX(Doc_Catalogo!$B:$B,MATCH(G166,Doc_Catalogo!$A:$A,0)),"") -> Comprovante de Residencia | I166: enviado
A167: ENV-0166 | B167: OBR-003 | C167: =IFERROR(INDEX(Obras!$B:$B,MATCH(B167,Obras!$A:$A,0)),"") -> Hospital SC | D167: Colaborador | E167: COL-041 | F167: =IFERROR(INDEX(Colaboradores!$E:$E,MATCH(E167,Colaboradores!$A:$A,0)),"") -> GABRIEL SCHURT (proprietario) | G167: DOC-044 | H167: =IFERROR(INDEX(Doc_Catalogo!$B:$B,MATCH(G167,Doc_Catalogo!$A:$A,0)),"") -> Comprovante de Residencia | I167: enviado
A168: ENV-0167 | B168: OBR-003 | C168: =IFERROR(INDEX(Obras!$B:$B,MATCH(B168,Obras!$A:$A,0)),"") -> Hospital SC | D168: Colaborador | E168: COL-002 | F168: =IFERROR(INDEX(Colaboradores!$E:$E,MATCH(E168,Colaboradores!$A:$A,0)),"") -> SILVIO SCHURT | G168: DOC-034 | H168: =IFERROR(INDEX(Doc_Catalogo!$B:$B,MATCH(G168,Doc_Catalogo!$A:$A,0)),"") -> Ficha de Registro | I168: pendente
A169: ENV-0168 | B169: OBR-003 | C169: =IFERROR(INDEX(Obras!$B:$B,MATCH(B169,Obras!$A:$A,0)),"") -> Hospital SC | D169: Colaborador | E169: COL-008 | F169: =IFERROR(INDEX(Colaboradores!$E:$E,MATCH(E169,Colaboradores!$A:$A,0)),"") -> DANIEL SCHURT | G169: DOC-034 | H169: =IFERROR(INDEX(Doc_Catalogo!$B:$B,MATCH(G169,Doc_Catalogo!$A:$A,0)),"") -> Ficha de Registro | I169: pendente
A170: ENV-0169 | B170: OBR-003 | C170: =IFERROR(INDEX(Obras!$B:$B,MATCH(B170,Obras!$A:$A,0)),"") -> Hospital SC | D170: Colaborador | E170: COL-041 | F170: =IFERROR(INDEX(Colaboradores!$E:$E,MATCH(E170,Colaboradores!$A:$A,0)),"") -> GABRIEL SCHURT (proprietario) | G170: DOC-034 | H170: =IFERROR(INDEX(Doc_Catalogo!$B:$B,MATCH(G170,Doc_Catalogo!$A:$A,0)),"") -> Ficha de Registro | I170: pendente
A171: ENV-0170 | B171: OBR-003 | C171: =IFERROR(INDEX(Obras!$B:$B,MATCH(B171,Obras!$A:$A,0)),"") -> Hospital SC | D171: Colaborador | E171: COL-018 | F171: =IFERROR(INDEX(Colaboradores!$E:$E,MATCH(E171,Colaboradores!$A:$A,0)),"") -> FABIO LEANDRO DE FREITAS ASSIS | G171: DOC-034 | H171: =IFERROR(INDEX(Doc_Catalogo!$B:$B,MATCH(G171,Doc_Catalogo!$A:$A,0)),"") -> Ficha de Registro | I171: pendente
A172: ENV-0171 | B172: OBR-003 | C172: =IFERROR(INDEX(Obras!$B:$B,MATCH(B172,Obras!$A:$A,0)),"") -> Hospital SC | D172: Colaborador | E172: COL-002 | F172: =IFERROR(INDEX(Colaboradores!$E:$E,MATCH(E172,Colaboradores!$A:$A,0)),"") -> SILVIO SCHURT | G172: DOC-046 | H172: =IFERROR(INDEX(Doc_Catalogo!$B:$B,MATCH(G172,Doc_Catalogo!$A:$A,0)),"") -> Demonstrativo e-Social com vinculo empregaticio | I172: enviado
A173: ENV-0172 | B173: OBR-003 | C173: =IFERROR(INDEX(Obras!$B:$B,MATCH(B173,Obras!$A:$A,0)),"") -> Hospital SC | D173: Colaborador | E173: COL-008 | F173: =IFERROR(INDEX(Colaboradores!$E:$E,MATCH(E173,Colaboradores!$A:$A,0)),"") -> DANIEL SCHURT | G173: DOC-046 | H173: =IFERROR(INDEX(Doc_Catalogo!$B:$B,MATCH(G173,Doc_Catalogo!$A:$A,0)),"") -> Demonstrativo e-Social com vinculo empregaticio | I173: enviado
A174: ENV-0173 | B174: OBR-003 | C174: =IFERROR(INDEX(Obras!$B:$B,MATCH(B174,Obras!$A:$A,0)),"") -> Hospital SC | D174: Colaborador | E174: COL-041 | F174: =IFERROR(INDEX(Colaboradores!$E:$E,MATCH(E174,Colaboradores!$A:$A,0)),"") -> GABRIEL SCHURT (proprietario) | G174: DOC-046 | H174: =IFERROR(INDEX(Doc_Catalogo!$B:$B,MATCH(G174,Doc_Catalogo!$A:$A,0)),"") -> Demonstrativo e-Social com vinculo empregaticio | I174: enviado
A175: ENV-0174 | B175: OBR-003 | C175: =IFERROR(INDEX(Obras!$B:$B,MATCH(B175,Obras!$A:$A,0)),"") -> Hospital SC | D175: Colaborador | E175: COL-002 | F175: =IFERROR(INDEX(Colaboradores!$E:$E,MATCH(E175,Colaboradores!$A:$A,0)),"") -> SILVIO SCHURT | G175: DOC-004 | H175: =IFERROR(INDEX(Doc_Catalogo!$B:$B,MATCH(G175,Doc_Catalogo!$A:$A,0)),"") -> ASO | I175: enviado
A176: ENV-0175 | B176: OBR-003 | C176: =IFERROR(INDEX(Obras!$B:$B,MATCH(B176,Obras!$A:$A,0)),"") -> Hospital SC | D176: Colaborador | E176: COL-008 | F176: =IFERROR(INDEX(Colaboradores!$E:$E,MATCH(E176,Colaboradores!$A:$A,0)),"") -> DANIEL SCHURT | G176: DOC-004 | H176: =IFERROR(INDEX(Doc_Catalogo!$B:$B,MATCH(G176,Doc_Catalogo!$A:$A,0)),"") -> ASO | I176: enviado
... A253: ENV-0252 | B253: OBR-004 | C253: =IFERROR(INDEX(Obras!$B:$B,MATCH(B253,Obras!$A:$A,0)),"") -> Paraguaçu | D253: Colaborador | E253: COL-028 | F253: =IFERROR(INDEX(Colaboradores!$E:$E,MATCH(E253,Colaboradores!$A:$A,0)),"") -> RAFAEL PEREIRA DE LIMA | G253: DOC-036 | H253: =IFERROR(INDEX(Doc_Catalogo!$B:$B,MATCH(G253,Doc_Catalogo!$A:$A,0)),"") -> Contrato de Trabalho | I253: enviado
A254: ENV-0253 | B254: OBR-004 | C254: =IFERROR(INDEX(Obras!$B:$B,MATCH(B254,Obras!$A:$A,0)),"") -> Paraguaçu | D254: Colaborador | E254: COL-028 | F254: =IFERROR(INDEX(Colaboradores!$E:$E,MATCH(E254,Colaboradores!$A:$A,0)),"") -> RAFAEL PEREIRA DE LIMA | G254: DOC-043 | H254: =IFERROR(INDEX(Doc_Catalogo!$B:$B,MATCH(G254,Doc_Catalogo!$A:$A,0)),"") -> Documento com foto (RG ou CNH apresentado) | I254: pendente | J254: Valor original na planilha antiga: 'CNH' (nao era um simples OK) — confirmar interpretacao.
A255: ENV-0254 | B255: OBR-004 | C255: =IFERROR(INDEX(Obras!$B:$B,MATCH(B255,Obras!$A:$A,0)),"") -> Paraguaçu | D255: Colaborador | E255: COL-028 | F255: =IFERROR(INDEX(Colaboradores!$E:$E,MATCH(E255,Colaboradores!$A:$A,0)),"") -> RAFAEL PEREIRA DE LIMA | G255: DOC-004 | H255: =IFERROR(INDEX(Doc_Catalogo!$B:$B,MATCH(G255,Doc_Catalogo!$A:$A,0)),"") -> ASO | I255: enviado
A256: ENV-0255 | B256: OBR-004 | C256: =IFERROR(INDEX(Obras!$B:$B,MATCH(B256,Obras!$A:$A,0)),"") -> Paraguaçu | D256: Colaborador | E256: COL-028 | F256: =IFERROR(INDEX(Colaboradores!$E:$E,MATCH(E256,Colaboradores!$A:$A,0)),"") -> RAFAEL PEREIRA DE LIMA | G256: DOC-040 | H256: =IFERROR(INDEX(Doc_Catalogo!$B:$B,MATCH(G256,Doc_Catalogo!$A:$A,0)),"") -> Ficha de EPI Atualizada | I256: enviado
A257: ENV-0256 | B257: OBR-004 | C257: =IFERROR(INDEX(Obras!$B:$B,MATCH(B257,Obras!$A:$A,0)),"") -> Paraguaçu | D257: Colaborador | E257: COL-028 | F257: =IFERROR(INDEX(Colaboradores!$E:$E,MATCH(E257,Colaboradores!$A:$A,0)),"") -> RAFAEL PEREIRA DE LIMA | G257: DOC-039 | H257: =IFERROR(INDEX(Doc_Catalogo!$B:$B,MATCH(G257,Doc_Catalogo!$A:$A,0)),"") -> Ordem de Servico | I257: enviado
A258: ENV-0257 | B258: OBR-004 | C258: =IFERROR(INDEX(Obras!$B:$B,MATCH(B258,Obras!$A:$A,0)),"") -> Paraguaçu | D258: Colaborador | E258: COL-028 | F258: =IFERROR(INDEX(Colaboradores!$E:$E,MATCH(E258,Colaboradores!$A:$A,0)),"") -> RAFAEL PEREIRA DE LIMA | G258: DOC-009 | H258: =IFERROR(INDEX(Doc_Catalogo!$B:$B,MATCH(G258,Doc_Catalogo!$A:$A,0)),"") -> Certificado da NR06 — Colaborador | I258: enviado
A259: ENV-0258 | B259: OBR-004 | C259: =IFERROR(INDEX(Obras!$B:$B,MATCH(B259,Obras!$A:$A,0)),"") -> Paraguaçu | D259: Colaborador | E259: COL-028 | F259: =IFERROR(INDEX(Colaboradores!$E:$E,MATCH(E259,Colaboradores!$A:$A,0)),"") -> RAFAEL PEREIRA DE LIMA | G259: DOC-017 | H259: =IFERROR(INDEX(Doc_Catalogo!$B:$B,MATCH(G259,Doc_Catalogo!$A:$A,0)),"") -> Certificado da NR12 — Colaborador | I259: enviado
A260: ENV-0259 | B260: OBR-004 | C260: =IFERROR(INDEX(Obras!$B:$B,MATCH(B260,Obras!$A:$A,0)),"") -> Paraguaçu | D260: Colaborador | E260: COL-028 | F260: =IFERROR(INDEX(Colaboradores!$E:$E,MATCH(E260,Colaboradores!$A:$A,0)),"") -> RAFAEL PEREIRA DE LIMA | G260: DOC-023 | H260: =IFERROR(INDEX(Doc_Catalogo!$B:$B,MATCH(G260,Doc_Catalogo!$A:$A,0)),"") -> Certificado da NR18 — Colaborador | I260: enviado
A261: ENV-0260 | B261: OBR-004 | C261: =IFERROR(INDEX(Obras!$B:$B,MATCH(B261,Obras!$A:$A,0)),"") -> Paraguaçu | D261: Colaborador | E261: COL-028 | F261: =IFERROR(INDEX(Colaboradores!$E:$E,MATCH(E261,Colaboradores!$A:$A,0)),"") -> RAFAEL PEREIRA DE LIMA | G261: DOC-031 | H261: =IFERROR(INDEX(Doc_Catalogo!$B:$B,MATCH(G261,Doc_Catalogo!$A:$A,0)),"") -> Certificado da NR35 — Colaborador | I261: enviado
A262: ENV-0261 | B262: OBR-004 | C262: =IFERROR(INDEX(Obras!$B:$B,MATCH(B262,Obras!$A:$A,0)),"") -> Paraguaçu | D262: Empresa | E262: EMP-020 | F262: =IFERROR(INDEX(Empresas!$D:$D,MATCH(E262,Empresas!$A:$A,0)),"") -> RN SCAL SERVICOS LTDA | G262: DOC-049 | H262: =IFERROR(INDEX(Doc_Catalogo!$B:$B,MATCH(G262,Doc_Catalogo!$A:$A,0)),"") -> PGR | I262: enviado
A263: ENV-0262 | B263: OBR-005 | C263: =IFERROR(INDEX(Obras!$B:$B,MATCH(B263,Obras!$A:$A,0)),"") -> Vip Gales | D263: Empresa | E263: EMP-013 | F263: =IFERROR(INDEX(Empresas!$D:$D,MATCH(E263,Empresas!$A:$A,0)),"") -> LR GRUP ELEVADORES LTDA | G263: DOC-050 | H263: =IFERROR(INDEX(Doc_Catalogo!$B:$B,MATCH(G263,Doc_Catalogo!$A:$A,0)),"") -> PCMSO | I263: enviado
A264: ENV-0263 | B264: OBR-005 | C264: =IFERROR(INDEX(Obras!$B:$B,MATCH(B264,Obras!$A:$A,0)),"") -> Vip Gales | D264: Empresa | E264: EMP-013 | F264: =IFERROR(INDEX(Empresas!$D:$D,MATCH(E264,Empresas!$A:$A,0)),"") -> LR GRUP ELEVADORES LTDA | G264: DOC-049 | H264: =IFERROR(INDEX(Doc_Catalogo!$B:$B,MATCH(G264,Doc_Catalogo!$A:$A,0)),"") -> PGR | I264: enviado
...

Sheet Doc_Compliance_Obra
A1: ID | B1: ID_Obra | C1: Nome_Obra | D1: ID_Empresa | E1: ID_Colaborador | F1: ID_Documento | G1: Nome_Documento | H1: Competencia_AAAA_MM | I1: Data_Envio | J1: Status | K1: Observacao
A2: COMP-001 | B2: OBR-003 | C2: =IFERROR(INDEX(Obras!$B:$B,MATCH(B2,Obras!$A:$A,0)),"") -> Hospital SC | D2: EMP-006 | F2: DOC-071 | G2: =IFERROR(INDEX(Doc_Catalogo!$B:$B,MATCH(F2,Doc_Catalogo!$A:$A,0)),"") -> Comprovante de pagamento de FGTS | H2: 2026-08 | J2: pendente | K2: (exemplo) — a aba Hospital SC de Controle de Documentos.xlsx so registra 'OK/Nao tem' por documento, sem informar a competencia mensal — quando o controle mensal comecar a ser feito de verdade, preencher aqui.
